{
  "creds": {
    "noiseKey": {
      "private": {
        "type": "Buffer",
        "data": "sM9wWn4gT0Wec32kIT1RoEtEJv7+oKRGBSQIDYTTSkQ="
      },
      "public": {
        "type": "Buffer",
        "data": "F3AftQJcy8Zpy/V7lH2eMAT3pumLTLIR/fzzYbPJ7jk="
      }
    },
    "signedIdentityKey": {
      "private": {
        "type": "Buffer",
        "data": "+CowXA7oxN4HSV8186QZYBjX7QjNL0uQEix4BU7PXn4="
      },
      "public": {
        "type": "Buffer",
        "data": "7J4eZydT/mhRYa9XJDQVMSaUlqMkuefu4LJHjcRxtQY="
      }
    },
    "signedPreKey": {
      "keyPair": {
        "private": {
          "type": "Buffer",
          "data": "0LGYcyhOJ3jRwGmkVHnVgsz3AgF5QGWvjjBnbkI26m8="
        },
        "public": {
          "type": "Buffer",
          "data": "7WovcoFznnrGwUJ5ffQZt49qlPtWUnTRLPYap/dE7Ak="
        }
      },
      "signature": {
        "type": "Buffer",
        "data": "0OIgzpNpvlJ6LfnHaWxaC1rMwwy1O/g/yoaqBrFvFx7bd4eriAXJLsiv5q5IpSOiiC21ffJnirGETsyQU/HdCw=="
      },
      "keyId": 1
    },
    "registrationId": 223,
    "advSecretKey": "PMYwm5ZIfOL5AuqIJD+Ta2c2Bly+Dih2BdCb5kYmy+o=",
    "processedHistoryMessages": [
      {
        "key": {
          "remoteJid": "6285233963207@s.whatsapp.net",
          "fromMe": true,
          "id": "56955BD6A7B7C5C35D510EF96DCE555B"
        },
        "timestamp": 1657325579
      },
      {
        "key": {
          "remoteJid": "6285233963207@s.whatsapp.net",
          "fromMe": true,
          "id": "10B5703EFCE10B5793B2DB05EDED2913"
        },
        "timestamp": 1657325580
      },
      {
        "key": {
          "remoteJid": "6285233963207@s.whatsapp.net",
          "fromMe": true,
          "id": "AF4D5F7381ED74B09D73B2126758E850"
        },
        "timestamp": 1657325585
      }
    ],
    "nextPreKeyId": 31,
    "firstUnuploadedPreKeyId": 31,
    "accountSettings": {
      "unarchiveChats": false
    },
    "account": {
      "details": "CNneqJAFEPyPo5YGGAE=",
      "accountSignature": "F90rvyGPINfhkuy7KMnEtOMymF22EBaxzE0T3shiWznvOKJv0/368xZhzHY2Eb58b8CVDGqUeWbn129QzASiCw==",
      "deviceSignature": "2DJiocnLLvn9IWndy84b1DkZX4VmDYKo/PH6sMWk2l3L3SLUbsapGl6xoeeJAdHkFw4+e0FUpDh3hWnnfq3+Bg=="
    },
    "me": {
      "id": "6285233963207:20@s.whatsapp.net",
      "name": "BOT",
      "jid": "6285233963207@s.whatsapp.net"
    },
    "signalIdentities": [
      {
        "identifier": {
          "name": "6285233963207:20@s.whatsapp.net",
          "deviceId": 0
        },
        "identifierKey": {
          "type": "Buffer",
          "data": "BUhf1kkuQv/FGz0q0UMl7fG3+d17sjS5JifXjvYzqdsz"
        }
      }
    ],
    "platform": "smba",
    "lastAccountSyncTimestamp": 1657325567,
    "myAppStateKeyId": "AAAAAKg0"
  },
  "keys": {
    "preKeys": {
      "1": {
        "private": {
          "type": "Buffer",
          "data": "8GbvIebMkZ9mwjlgtcsUBxEGgko2cI7VA3911PyTJkM="
        },
        "public": {
          "type": "Buffer",
          "data": "fgm7gAj9RbNGonpO8g2DFo4Kqs8X+5twFMoN7FIapzM="
        }
      },
      "2": {
        "private": {
          "type": "Buffer",
          "data": "aKrKURcO+7Nl4+HBGOZsHnvtKttssfB5mPLe4oES3Hc="
        },
        "public": {
          "type": "Buffer",
          "data": "KGZ73bRslq/rQDeBbteCDK32YasaM2RlaorMIIPRYlg="
        }
      },
      "3": {
        "private": {
          "type": "Buffer",
          "data": "eFTxYRDvnKLo6cGKEUHZVxK792ec3XEvWg+b6mUei3E="
        },
        "public": {
          "type": "Buffer",
          "data": "dXIz6qHw5HvTlI7gTJoL4vp2QZC01DRcngdOoBWv2zg="
        }
      },
      "4": {
        "private": {
          "type": "Buffer",
          "data": "SOEtztZ5a244ZxZPswq8UL6bljdrd/gAxhY2YVvr/mQ="
        },
        "public": {
          "type": "Buffer",
          "data": "3PPKEBO08gxD78z+ViqdFD+erIqDv7yF2Flr7DHY1GE="
        }
      },
      "5": {
        "private": {
          "type": "Buffer",
          "data": "QBZ2q5eZ11ayp1Vo4rCooNc17aH+mwt81Ytwn+w191k="
        },
        "public": {
          "type": "Buffer",
          "data": "OT35dzCRAlNPh8+B3amF8zsXD+4Xlc4QalLQ85qfGy0="
        }
      },
      "6": {
        "private": {
          "type": "Buffer",
          "data": "qJ0g67gxUlmMsZBF2MVFK/bDo6Qf9Al+mECMawao0Wc="
        },
        "public": {
          "type": "Buffer",
          "data": "wRMtl7xKWp1NHHtm2K4GjypPm+KgIiGL98n5slFOxGU="
        }
      },
      "7": {
        "private": {
          "type": "Buffer",
          "data": "4GJyTbIIepswXoXlVWidb6pMnQfT5XoakBZU9Nz/znE="
        },
        "public": {
          "type": "Buffer",
          "data": "+/MocNNW/CPdbrl4WAQz2Gozn/XfXp6ogBQy/IDT2zs="
        }
      },
      "8": {
        "private": {
          "type": "Buffer",
          "data": "iHDNIUCH0atnMOPLTTOFa5CvSFk86UES6cO2MUnRs04="
        },
        "public": {
          "type": "Buffer",
          "data": "fQA/mjMC1rzktsOh3OsLkPgcxuFDmtNhC5gibA+NRis="
        }
      },
      "9": {
        "private": {
          "type": "Buffer",
          "data": "4Ie04qqRFZZ8xhVq2djS5giXPv5sdl1znCZJnmS0ons="
        },
        "public": {
          "type": "Buffer",
          "data": "n64XokjUuv9aURFXEi/E8kmhksJye9pGd2dpnyFCLwc="
        }
      },
      "10": {
        "private": {
          "type": "Buffer",
          "data": "mN3+a7Xzg8MxjO8yOqZlHiKt3aLmBrMqOZrDDZT3JUI="
        },
        "public": {
          "type": "Buffer",
          "data": "ISbgvwH6cTdS22x/cYANXhALP2lMu/4nHO3XYkXYunI="
        }
      },
      "11": {
        "private": {
          "type": "Buffer",
          "data": "UEqY2M1S5IKobgiaUnXwosxKIRqDuEbDn+lIFqHPUHI="
        },
        "public": {
          "type": "Buffer",
          "data": "Wgwiqap0NCVJu38yqJfu69ckSgxZKl0PPfLEJ2yRoQw="
        }
      },
      "12": {
        "private": {
          "type": "Buffer",
          "data": "AK+KvfR8soab6XNkyiOLT0Y5dv8PBNFO/7LjiFvJj2Q="
        },
        "public": {
          "type": "Buffer",
          "data": "7Ml8vUpzDiduY8k7PkJ5xLneyF+aOW8/JB3sG31Nxhs="
        }
      },
      "13": {
        "private": {
          "type": "Buffer",
          "data": "IFA/4YUg8und/chsW66Bp1miHCprdyDY7R1ts2SBR1M="
        },
        "public": {
          "type": "Buffer",
          "data": "vlTlDW/yR7XOaR5TM9pirPpe7iOP40s46grPRTyPqCQ="
        }
      },
      "14": {
        "private": {
          "type": "Buffer",
          "data": "MOTEJTPyi8KXneMMrOZkmkV8mh+O3DYt5x/mlfB2DVw="
        },
        "public": {
          "type": "Buffer",
          "data": "hczAqGCo66Mdra8J9pNlg8tWejKE5I/K/Sc2KvpLEwI="
        }
      },
      "15": {
        "private": {
          "type": "Buffer",
          "data": "YCpNGuDO4rE0mpF7pJrv2zUh0xdmNBD1pfGNt+SQcmA="
        },
        "public": {
          "type": "Buffer",
          "data": "oik9H/e0La3BU4plJovS5rjv4090fl+Fuyrmp2El3R0="
        }
      },
      "16": {
        "private": {
          "type": "Buffer",
          "data": "ILPth9FvHWaX6oJG4tiC44eZqt3n0QkffWP+Yr3OxVc="
        },
        "public": {
          "type": "Buffer",
          "data": "OI4Zgs2wJRz8VEsgKZHFpBVMRvcead71IjwllMRSeCA="
        }
      },
      "17": {
        "private": {
          "type": "Buffer",
          "data": "UL/StydcP6oyxGZy5fc8sl3nYLcRRAmE9nPvTSF55nM="
        },
        "public": {
          "type": "Buffer",
          "data": "bd4C8xM4dAoL36ua0EavCI1MXKRVBLb+l1PqH74rGgQ="
        }
      },
      "18": {
        "private": {
          "type": "Buffer",
          "data": "6Acvy9Kt65USDCgJ/NLBCrrHiwJ3YJkmHODT0anhD34="
        },
        "public": {
          "type": "Buffer",
          "data": "SgfVWRaoXojR9k823J2KI/grMJfP5kRhzJ54tTilsjU="
        }
      },
      "19": null,
      "20": {
        "private": {
          "type": "Buffer",
          "data": "iBKFn3niPEkPhJfNOMW25d6Yi3TP0QO1Dcgnxo612XE="
        },
        "public": {
          "type": "Buffer",
          "data": "o7uIyijAHr6jKloG1ErjfAfl0rWCXjQZkYoHc/A+rUU="
        }
      },
      "21": {
        "private": {
          "type": "Buffer",
          "data": "ALgk4v5yE2mYTooejcDNPo4mLqc5g08N+vhJPE6nqFk="
        },
        "public": {
          "type": "Buffer",
          "data": "Az1JV6aPqkxNdur4cfuvQB1hZEXDigT2ne9XN8I7TyM="
        }
      },
      "22": {
        "private": {
          "type": "Buffer",
          "data": "mO+1WXCDlPE9Ky3RxxwkH+FeDV0Au0GTCw8ffdRgsXM="
        },
        "public": {
          "type": "Buffer",
          "data": "wdZW3FpZs+v3LQccFUALwXDs86xwdxAJO+HmBLYlznU="
        }
      },
      "23": {
        "private": {
          "type": "Buffer",
          "data": "MCA9/ak+4MhKI4rVPLv9o9I0GWYw9DrtNLksqGEML2s="
        },
        "public": {
          "type": "Buffer",
          "data": "NTXCmen+vOB7XyIABr9NiZYmKmJlok6xKHPr9bCbcFw="
        }
      },
      "24": {
        "private": {
          "type": "Buffer",
          "data": "aOmXN5jLz+V6sRqqSP3gfnLKNOc3dGWlY/c/kEiEP10="
        },
        "public": {
          "type": "Buffer",
          "data": "lI8aqIharUl52O3D5FM5VtejkwJATonLP18IpXuv1yE="
        }
      },
      "25": {
        "private": {
          "type": "Buffer",
          "data": "kDcFuCMMRSECuOTUa1nj1EIOYp69FndERZDl+YMyDFI="
        },
        "public": {
          "type": "Buffer",
          "data": "lk5s39GI2mFpMInhTe7WMoKdcr375JN9uy5jn6MavWQ="
        }
      },
      "26": {
        "private": {
          "type": "Buffer",
          "data": "UJTk6ghQ1pjLZ5YblrRwLShJrv/NBLjiBVnN/PHeemQ="
        },
        "public": {
          "type": "Buffer",
          "data": "PZq/LK23rr6iqXcZL2CXW+SedV57ShrrwWVHwZPB5wU="
        }
      },
      "27": {
        "private": {
          "type": "Buffer",
          "data": "OKxHGhoZ6SNHHT3EJQd+JYgmVppf/CvClVUd3vbwml0="
        },
        "public": {
          "type": "Buffer",
          "data": "fAThxNNTNIGdnUjitSjnN8AerET+D55AdG8e63u0f0Q="
        }
      },
      "28": {
        "private": {
          "type": "Buffer",
          "data": "8GLLxf1VmohqrO+kawdafnuz/CymA80OLkZhn9fMXng="
        },
        "public": {
          "type": "Buffer",
          "data": "H9GPBB0clAlyBPM1SWZaIOrwyDv62WGSi/Q/9bvc+RM="
        }
      },
      "29": {
        "private": {
          "type": "Buffer",
          "data": "AMnGLxVfBz5W/vyXUvuw8eVHbQMZR43A9BEo5F5nt18="
        },
        "public": {
          "type": "Buffer",
          "data": "TeFoEL+g61Z/YIxWqfnFpttZ6D3Q1MVdsaCY1xOJTyw="
        }
      },
      "30": {
        "private": {
          "type": "Buffer",
          "data": "+JY8wWKyy0GU47Gxq59uyI2a+H0tViJZRMaBDqvOBkU="
        },
        "public": {
          "type": "Buffer",
          "data": "mhE1xny+5a9YC7/ods0b8g3WlXgkMDQ0vH70+8J6fAE="
        }
      }
    },
    "sessions": {
      "6285233963207.0": {
        "_sessions": {
          "BTVzxovJgugO+plDiVEwv2s6rRO34gCbjXCbz18HluYH": {
            "registrationId": 396947324,
            "currentRatchet": {
              "ephemeralKeyPair": {
                "pubKey": "BXptT3ah60SFEzfCl+vLvRfV4lFwqajYaCzp5lU9MEcz",
                "privKey": "4KajxTyHe13kpC7iw4BZ4ZaLHVoxdZfchJz1rbhSwlI="
              },
              "lastRemoteEphemeralKey": "BQT1nG20lOHXPtTyFqrzX7sNhvYzEE50o841mw3WjvwN",
              "previousCounter": 0,
              "rootKey": "RzuSrSpI1dtMWr0kGE5gx+bWpGDVF6I3673HwwjmOno="
            },
            "indexInfo": {
              "baseKey": "BTVzxovJgugO+plDiVEwv2s6rRO34gCbjXCbz18HluYH",
              "baseKeyType": 2,
              "closed": -1,
              "used": 1657325578401,
              "created": 1657325578401,
              "remoteIdentityKey": "BUhf1kkuQv/FGz0q0UMl7fG3+d17sjS5JifXjvYzqdsz"
            },
            "_chains": {
              "BQT1nG20lOHXPtTyFqrzX7sNhvYzEE50o841mw3WjvwN": {
                "chainKey": {
                  "counter": 6,
                  "key": "NhI4Lm0EpS1hvREbEiVNibuLIKWNfWmbI/W3Cz9/So8="
                },
                "chainType": 2,
                "messageKeys": {}
              },
              "BXptT3ah60SFEzfCl+vLvRfV4lFwqajYaCzp5lU9MEcz": {
                "chainKey": {
                  "counter": -1,
                  "key": "wel4JA4b4Doh0wdjRboGfrRImU2Ye8gGTQekccvXzuI="
                },
                "chainType": 1,
                "messageKeys": {}
              }
            }
          }
        },
        "version": "v1"
      }
    },
    "appStateSyncKeys": {
      "AAAAAKg0": {
        "keyData": "DHzkbTweKPh2WwoBiDCwIvsgdr19gGkmkOh3RXkbBfk=",
        "fingerprint": {
          "rawId": 1376399193,
          "currentIndex": 1,
          "deviceIndexes": [
            0,
            1
          ]
        },
        "timestamp": "1657325576442"
      }
    },
    "appStateVersions": {
      "critical_block": {
        "version": 1,
        "hash": {
          "type": "Buffer",
          "data": "xQMkNMbpANeI9K3NLF7qjPXjvImNTVTB09IoMfuMYwczdhR3v8WyyEYReqfy8rCV1z4ClIBwZuslrP4MNCtdXhJMeZiSJ5UL9pmeJBoMQ2topxZMKGfPGWePVFlMENgyWS/Nrg0cV6gh+3JVwU/9XsIwa8Pncgc9BYWx/I5pTUU="
        },
        "indexValueMap": {
          "werrSmQ8tKGWBtVbwef7S0LEFT2P88hsAfS9W4VyauY=": {
            "valueMac": {
              "type": "Buffer",
              "data": "oEuW0nNnfQR7nTeACxCJpCEInJIXMlpG6bU/+PMdDaw="
            }
          },
          "x7oIX/0dM0VGNtR2I5oULkrao1gYHi46Q+8MMc2GFR4=": {
            "valueMac": {
              "type": "Buffer",
              "data": "XCD0SgEhZzOW2WzcuubNsTqgK5qWpfSVJSioAtFec9E="
            }
          }
        }
      },
      "regular": {
        "version": 1,
        "hash": {
          "type": "Buffer",
          "data": "thbz53c4/IsZc+EXS0CLq8xkLA8tPZSc1Ac8ofxeqezyxCRFiSJIYZKnqwfHUhS36XZUvBVefwksfDw7pAWSgWN/8u3zWgyO+VmudEH+khREAOVefiwSwm4txspteKCd+K+6BACbPSHLG0JH37GzivVYqybcF8NTL7gvyLWFYTI="
        },
        "indexValueMap": {
          "SXI2ViYmaKjyq4sPNlmCv8nbbi+BEJ7QYBNNl2uJ4Lw=": {
            "valueMac": {
              "type": "Buffer",
              "data": "Tgl5U4v8tZCJAOMM9T+4V2Eg3eLtx2MBrHJYC7GTbaA="
            }
          },
          "Pe1fKWc6Qv/UwteZPj8DrT7nbOOJ6CtyowHpbTkFjIY=": {
            "valueMac": {
              "type": "Buffer",
              "data": "xBNYFFuZPCgrGATA2bJG8dVtgZ97XKOsrsdXcn7KfkQ="
            }
          },
          "bPEHB6k8/1DB/6cYIzcW95rOMJW3VsyfrmiAc3d7lz8=": {
            "valueMac": {
              "type": "Buffer",
              "data": "bZqolCYX3wcKb7q/7yjErxX5hhcOOWCfLwg036lVcgE="
            }
          },
          "rEMXKHzVnqJDmwHB1J8oNPRJgVLJm36cCifcIPpdfZQ=": {
            "valueMac": {
              "type": "Buffer",
              "data": "8aLq+enFFDwTWMeZfrEULxBbuXOBMrNCGscPPExzuyI="
            }
          },
          "Pxalx2JaKVaI2ZaZ+bdoWAiRjJ6Sl2ppIbcnbFOQaBA=": {
            "valueMac": {
              "type": "Buffer",
              "data": "LKiK/4VBc66sBUv9XVCvCwDQNNKk09CnEVFGfXZg3jU="
            }
          },
          "A44lP0UQDf4hjHxenvtnGtYhgewtWBvV8EvKOqfSsyg=": {
            "valueMac": {
              "type": "Buffer",
              "data": "9IIXWdNZin6X4Q0j84lmrE9NPUphY1otsq7UbFEuG7g="
            }
          }
        }
      },
      "critical_unblock_low": {
        "version": 1,
        "hash": {
          "type": "Buffer",
          "data": "5zlpkOmTj3f+cIyz0xMHvvQmohWl1tGzaYw8MPsn44JbcpEZ2CWZg+dqy5Ri7CV9cxm+jlvq8t+8Ad5OrBeJC7ceU9oFMNfYenmSuZf8g0CvEEwaNRLU9PcoKXQKv22gF0xQAMoavyKe79aAx1cQKr3e5gSpyk555XYJHXABbko="
        },
        "indexValueMap": {
          "hxZsnEiHcq0TiIA9QEjMng+dI9Wj+Q28AUNTdGmlwWw=": {
            "valueMac": {
              "type": "Buffer",
              "data": "CImZYDuuxbXlzHER7p8aT5fT/Zj5L0WHHXPkkg/D3rI="
            }
          },
          "ZN3mNcPjK1PLkiXO4eVGh68mXOZaAAtB3VSAPs9YbFo=": {
            "valueMac": {
              "type": "Buffer",
              "data": "MxWPzAGqxZ9wNEmRSia4glWhE6Wl34cG0MIS4tAWoaI="
            }
          },
          "VJrmKwmnnLVu7kFLukcRRcJpS5BlTIa1/tTbUKcLp6Q=": {
            "valueMac": {
              "type": "Buffer",
              "data": "4RkHbUeP+TG8qMWTkuxO+LMVS0b2eT3NLjK3YEml30M="
            }
          },
          "l1LLys+1pUkZS5xh9C5zh89flRk2KTwzbKDuWHLNabc=": {
            "valueMac": {
              "type": "Buffer",
              "data": "H0P2CnDqKAn5kRlUGLr0j/lJnWnF5jw0KHSZklwbeyA="
            }
          },
          "idkdjkDopokAjbORugHCbjFelmmVciEaCCDaXdml3Ls=": {
            "valueMac": {
              "type": "Buffer",
              "data": "Q6tmJwfBsnJDCqECeLtElIWKxbYQiArmTMGTW1nten0="
            }
          },
          "mRbngrs1eIAjkVk839i8Bs1CNGvVvS3bNTTpPDqabbg=": {
            "valueMac": {
              "type": "Buffer",
              "data": "s3PmrEC1tHR5uq/e18LSNe8QSToc3qkej6fJzIR+ZyM="
            }
          },
          "bDI6mSGldaD64z6rGEc4vtRjFddw8EZNqSg2hAjyZvk=": {
            "valueMac": {
              "type": "Buffer",
              "data": "kMyJDzYkr+Tee/loGeeB5flG1+ChylMP4TNf6hjco+4="
            }
          },
          "hN3n0z0/NgxY1hJi+hZOd28ofWHYkj9y4+WRSFk3e5M=": {
            "valueMac": {
              "type": "Buffer",
              "data": "WP70lfxQ9Czmpqb+np8sE34uqrVIZ1mUfAQpxJVfxGM="
            }
          },
          "bce9kUoFAwZ2/MNOwXRwrLN97FYq53ubRPF9iFQV1Po=": {
            "valueMac": {
              "type": "Buffer",
              "data": "rE1CW47xs15QaleKwMyP1W32yGEAm/AiWOfN80DLm4g="
            }
          },
          "cN9OddU5FKVcnCP1HeSTNUq/zbVhmMFyVb7XhqhdRuA=": {
            "valueMac": {
              "type": "Buffer",
              "data": "cDw4QS/6ittWvuZPReG0/CY948u+H1Q/y41e3WXMkKY="
            }
          },
          "X8LQzZMKFZ+Bie2EIngH6vyw1K5yhYlVH5a7c+1edYg=": {
            "valueMac": {
              "type": "Buffer",
              "data": "bs3mAHXokKwg37VExCNrXwGuaA00BRj8ZNqFf0WB34E="
            }
          },
          "GV+0SidtqgrD/ncU2watFGr5r5FMz1tI3BPNgdOW94I=": {
            "valueMac": {
              "type": "Buffer",
              "data": "fsQlC1ivLi8N1LXBiy5mb9AdEhEITnX7OpPA60lNcb8="
            }
          },
          "sglYSkYT6Xs4wzADt1y7o3K5v+goB9ACefT3MP92HkQ=": {
            "valueMac": {
              "type": "Buffer",
              "data": "9pkhznn35/xB9IhWLgdlOeDQDw7ibSFWxxNok8TZQdU="
            }
          },
          "pkulJM1HqCJiswvDYQmkFRl7VPCl5NYn1DX5o7eBaY8=": {
            "valueMac": {
              "type": "Buffer",
              "data": "QbXdxFafdxQQgqAUEQQcdqfeTh9IkkmckM8DsZRQN5c="
            }
          },
          "ao/xVkiCnhqDWY8avEnp1r6M/zf1hqMF93hpDKQexQE=": {
            "valueMac": {
              "type": "Buffer",
              "data": "sLt3z1rEGyPLhurHDRdFPdypvjRjrjLaE8PgJQnYdtM="
            }
          },
          "vtnIObYUCJzWqUwdzI+x/KCuQDMmvvtd1hBOWSNK3Lw=": {
            "valueMac": {
              "type": "Buffer",
              "data": "Fm20b1ikMDAwmaLDfZqAEM4PxgnChVISLXBoW03bucw="
            }
          },
          "yYJzICfynR7IZEb6oKVOQgz4DLp0eLh8rFqyE4DhTOg=": {
            "valueMac": {
              "type": "Buffer",
              "data": "hFDUFbxBAQXJgTQO2ehhpzzKzKDMlVYdlKw2vD0mEns="
            }
          },
          "pObBRYLuNnLXBBdG7yOn29MXKhV471KFnBuerWdAmJU=": {
            "valueMac": {
              "type": "Buffer",
              "data": "9V0LHpFcSUUrIvPRK0z3ldYWYzlhG9r5Sb0R6hIZN9E="
            }
          },
          "dbfIDKsr3rrxCdLR2hzyjvD/pa/iB0O+bgK8V1v4Bmw=": {
            "valueMac": {
              "type": "Buffer",
              "data": "njZ9VrPHkAdRj0TghE56FqJw9k8GD+QLF8uSrGzliB4="
            }
          },
          "jksOMut7Mi5mfhm+Jrp2Xk5UbFi/1xf2lxm4cByn3Bo=": {
            "valueMac": {
              "type": "Buffer",
              "data": "0KfTuxbbuVMUW5NpGZqqlxVicxUadyTXDat7zxpOtkM="
            }
          },
          "XgMz3v+BMzqLKDX/ObW1xBTqQMVmfTDg1UmZAWepmjM=": {
            "valueMac": {
              "type": "Buffer",
              "data": "bzocSDmT+IS0XSaBk6v66DPJRC5sfgQogCPYZP3J9No="
            }
          },
          "izjLmSt6J2dNOp0ZnO/7y21/dkY4qyJEYGy7d3xCBuI=": {
            "valueMac": {
              "type": "Buffer",
              "data": "lfAVjDAplraZnCf1aRGsmyH5q6p9EHtVzfbFKbLodM0="
            }
          },
          "6jWXi5cy4UFp3goafafHAoCzyN39t+IHeBup3y0eX5Y=": {
            "valueMac": {
              "type": "Buffer",
              "data": "xoMRupe/q7E8egaV6IXNTOO0h6+klDuAdzSS6TgQbmU="
            }
          },
          "JocT5W965qEjVbusG+lLjWWn22NWOaE2sooD7/hNIz4=": {
            "valueMac": {
              "type": "Buffer",
              "data": "BpVfw52iY9rN6cFjsLIdumLiWX3Qi4KF3REm6UWurVY="
            }
          },
          "oe5HJT8aCDdCR2g4sE26dclE4sZ1DMHzn6lfNPEDDio=": {
            "valueMac": {
              "type": "Buffer",
              "data": "tYR7McnYWHTtCJrR3OVxDc7eqq2bSd5GCSBwI+rK3R8="
            }
          },
          "NEF8K7twi9jYkjdCVq5Z+pKefLLvzEdg3bHs5jGVU2U=": {
            "valueMac": {
              "type": "Buffer",
              "data": "EKCw59ACw3W4ASBzC2xjsRIa3m8awjoajfsTpnQcVkQ="
            }
          },
          "+IqIf0MNdJTp2Y0LacEfhEFvJCAo60ZcHzSjsbkdjS8=": {
            "valueMac": {
              "type": "Buffer",
              "data": "9mHaCfhWC6EkUbRz8lFXtybY7lQSZXV41ufrrIu4qDU="
            }
          },
          "l66wDaOqi3jvUGD3HzQzoz53EInNaURv01fDr463guc=": {
            "valueMac": {
              "type": "Buffer",
              "data": "hlZJHfP6IOGxwB2zK/l1p8uw7q7p0ydWr4fnyv5i8aE="
            }
          },
          "oXoDO7C4Krm9WJmEGOYOQRte4akxroTn2YbFFXh3aic=": {
            "valueMac": {
              "type": "Buffer",
              "data": "fiHnL3FLt0Ry7a0SQJ5x0hRUrYMPZT0Oh/yD9uY76r4="
            }
          },
          "OaV4hflBqcrLOlqQX1oNvwgkV4V86q3SRxV4xWRoChM=": {
            "valueMac": {
              "type": "Buffer",
              "data": "gp4KGFdElNdpDq/5tDB4crS3f354brKvoiFc9UC7cz8="
            }
          },
          "ICk4QQ1whX5RHuzI59Fxkzc18mZ8+Q3yA8hiUyIGwtg=": {
            "valueMac": {
              "type": "Buffer",
              "data": "YwM5fHsQmbezyL7gek3p7hpWLQD3u2f0IAe0IXAovKQ="
            }
          },
          "8qgldTUBTDCMCI08gXeEzTZ3D5/kyHMVQg4ttXPycqE=": {
            "valueMac": {
              "type": "Buffer",
              "data": "ipC4cUiue74TyTlKJS+cmbXpmXz/LpnJmrF7+9vt9Zk="
            }
          },
          "+v4z55E/3XdUXFHUk68kfiHy6082iJE4J3cGfugwm1A=": {
            "valueMac": {
              "type": "Buffer",
              "data": "68Y0Qq2zO9oBkQcNRgSUt/sd2HkH/Z7VhvsPuuOhXkw="
            }
          },
          "1p3QkTynMAijNkCAcNrYVfVbnx5/31/MDfOzK2Zqy1A=": {
            "valueMac": {
              "type": "Buffer",
              "data": "4wHEQVuUY4GKjGZ3qGq7fpWJXHoyAde22PR+gvjW/iw="
            }
          },
          "sWNfgq7ZAQXrAMpLTTdF021Xh3a4YmMYsp7SKiHfJ9o=": {
            "valueMac": {
              "type": "Buffer",
              "data": "DuGGd7EvXNtfdyBTAINrGyhqAdfYy+w70fAfM7NEFM8="
            }
          },
          "CB4OB11JHDIde9i/6d7gdp8Z/gSFK9zymm9m+2s7XxE=": {
            "valueMac": {
              "type": "Buffer",
              "data": "Pmt3/ZZFMhAouXs3PrQuao5PmsJgMGzji3smVYB3FlA="
            }
          },
          "5YBbM9Hof24InrmONjSbHifVypuiU/zrpnzUtUCf4kA=": {
            "valueMac": {
              "type": "Buffer",
              "data": "z12IpfV39dn7jAEKHWnOQPfjwwVRa0TrajvClmJJv1M="
            }
          },
          "KRJLwnyTRbBDONeEpaEbbzaSVfU5jdOpz9QXM1EFjFY=": {
            "valueMac": {
              "type": "Buffer",
              "data": "iqE477C/QvWVezwo2A9LxUJQs9ZIZDrAqMdpQQnhf6s="
            }
          },
          "9OPJFgruufASvkQV85FFJRc5I8BEnTS1+8wm8Q9OrFY=": {
            "valueMac": {
              "type": "Buffer",
              "data": "kA4Tr2SCeWL/dSzO2BPMxHRr7hxBsnGYbRXDm21ckUs="
            }
          },
          "eFKd3a6sL0JqyldzJvpz8ufAkuNxaZJX2Gep6igCTU8=": {
            "valueMac": {
              "type": "Buffer",
              "data": "TBjC3MCpMvCi1c3lODFKZ5AAQRMD1ez8fuVHzYzMUGU="
            }
          },
          "D1SjkQdgs2S1DhXlX3Zhu1GcXAgyTCO6hkzY/G+dVsI=": {
            "valueMac": {
              "type": "Buffer",
              "data": "Gx0KNDKxYnL+KyVwDpW2N/D+hAFnj+h5r8bvaVypKww="
            }
          },
          "L9ynddETf7juHoZ8x9lIRpQnti9U0hfAqiwnd1B9TSA=": {
            "valueMac": {
              "type": "Buffer",
              "data": "dGN4XjOygczZtwAu6yMTFrsY69ej57rZj4bYPfryhyw="
            }
          },
          "IyCX8ZY8nzglzXILBN/1tDidjv2hiQ7lTWfRpeN4GiM=": {
            "valueMac": {
              "type": "Buffer",
              "data": "8N4U8Tk7g3OxWnznqI3BM7hq8k1K5NQKK/gTkGifQJg="
            }
          },
          "ii1wxfe3xq9LU/U0XqNQXZHUhIq9FhfAWK4zJ3voy+k=": {
            "valueMac": {
              "type": "Buffer",
              "data": "bqA2n3kTBBpl/TFHO/azFr50elfmdjcDSUuRUMi8NlE="
            }
          },
          "LG7PEoLcr4d4/KYIzYqQEptNOXUzrpim5CGbhPKHtuI=": {
            "valueMac": {
              "type": "Buffer",
              "data": "nqaOVgA9w684Vixs0xpdzqcabeqCNUvpmvd0SKGzJnw="
            }
          },
          "lE0VE6QdCkbsEvd8uxPAO2cSKLWaSGfmyZMlNKba0WA=": {
            "valueMac": {
              "type": "Buffer",
              "data": "BE7V5mxh1EdtZ5S9R+LrLMbWMXfk3z0JISfJq33DRYQ="
            }
          },
          "mW68LIEx35nDcef4Cwiht05w5MZleMTmmWm5gip7ZNM=": {
            "valueMac": {
              "type": "Buffer",
              "data": "ocCx7N4qY+9zyx82ZoqWglgIaESgCXtLIHSUnIJ9nw0="
            }
          },
          "BFEB7rUxVbA/Mcjiqd3bip+9O1UVQWMjcF53YSBBeGw=": {
            "valueMac": {
              "type": "Buffer",
              "data": "mdpmxfwjf8yg9oFSG4+M7XVU+nJUpmWMEmuRI9x9a6g="
            }
          },
          "cPUd1vj5wePedbaFtk6DlQozEIeYtZiuHyYAXN5q7WE=": {
            "valueMac": {
              "type": "Buffer",
              "data": "bsFWMPVuerWBygegAiGDQXPICQE4FVoIA2y1ziRdGmg="
            }
          },
          "f3287Nf7OLFBpObDhVzAFpj3H4eQLfjw21qrEEDhTU8=": {
            "valueMac": {
              "type": "Buffer",
              "data": "bZOkXl+zOIVz3jdq6Sx12AIdEj8xUIJ1FkN111HkNmU="
            }
          },
          "+vuE2TK5LSzeWnUdztsRJxrqHp4hAIY2IRc76KTAMIw=": {
            "valueMac": {
              "type": "Buffer",
              "data": "kpd4O0lJGGt4ME4TLB/PgliJAjN41V3WzVkOCBCV2Hg="
            }
          },
          "ZI/dm13sRB30CvfL0MpVwMobeV64PyqduoIe5GkQAhA=": {
            "valueMac": {
              "type": "Buffer",
              "data": "OhA5n7mtLqPCqA+fEYVfmLVgpPtJft0Bq2ytmhu39xQ="
            }
          },
          "D8CGmPznLla2rYRqbqTGnddEyDWlO8frf0uH3nUf33o=": {
            "valueMac": {
              "type": "Buffer",
              "data": "3QHfB4WXkVFwwDY+sgXdixNxnqFzNnk92Vf2Ceeec70="
            }
          },
          "vNHAbCVl4zzjNBSkLqZDFeQbwB3uWCfsnrf2UQnL248=": {
            "valueMac": {
              "type": "Buffer",
              "data": "XDzhWle/jusEvY2/DTtKNnbzq8ghlEkLu41U0qQb4Bg="
            }
          },
          "WQXM+OPqT93QedV7F7W/HZv4t7rd29ZgNLLmAN7sOUw=": {
            "valueMac": {
              "type": "Buffer",
              "data": "AXIrzjYYgukXxZMR9CjmD8yGBEZKo6CuZYZBXUa5dis="
            }
          },
          "w+vPGfNLfA1LhMxSk9yagTTa2yAUraaBXH2NDWhYaRw=": {
            "valueMac": {
              "type": "Buffer",
              "data": "nZhgrAnJvV2zqZO9ea8rFkkUAK/qjjVWOTYcOIlPbS0="
            }
          },
          "DrEOB/x1w0LUs93NT6ES+sa7mIUQ3Hbb3WT1BWtqfHY=": {
            "valueMac": {
              "type": "Buffer",
              "data": "0wLlbuuYgtfxjAl25fPgporND2sMVGsBA3dGNttFW2Y="
            }
          },
          "KjFqJpF0q3W8v0TdDr4u9KbnG0kVgueHIbOTnx/aboY=": {
            "valueMac": {
              "type": "Buffer",
              "data": "PRSafH/KAqk2vX/ECIDwL/ncLVIHPKwWnEuw69nWwTU="
            }
          },
          "FpCLAief8j2WSfT0UYe+QhL61TDs+8c8/PbI/UayeJU=": {
            "valueMac": {
              "type": "Buffer",
              "data": "RdkkXx1gQc0wXI5zSRd/NFQdUBF/Cf+XskvEZWYvkYs="
            }
          },
          "tnGcgGbXmt8RBFTucHBWuWhGXX6orjDlRj3ykAjkrK4=": {
            "valueMac": {
              "type": "Buffer",
              "data": "DLU6qQsEL55nL+hHFCxduviUZ55QpSJ3YydwnyjIBkM="
            }
          },
          "92C/GLsUObrP24vsj2QgWHcrhbRSVOkYJKfRGo7J5RY=": {
            "valueMac": {
              "type": "Buffer",
              "data": "e1RaFvMbJNeu1kN3c23qDU2t9ajc47Ofrfg02HuSz64="
            }
          },
          "bjpYk2/+5FqKisDNfLw+EiJcEbWYZawPfaiNfdb9/hE=": {
            "valueMac": {
              "type": "Buffer",
              "data": "ONRJS4mME6acbZfz6eDBicjFiTVosuOd7U+SWbUXegk="
            }
          },
          "gt6ysyFSVOHSX8T84uUtmR6WOlGjJFXNg65/ZqTZN7o=": {
            "valueMac": {
              "type": "Buffer",
              "data": "rjE3kUfw5rxD7hTOUNJ9IrYdLpC8LEXQElhKa/cSQs4="
            }
          },
          "CMOP3F8extLgJoonpR8GOIf5ZFBsB80kSkamx2XjBUU=": {
            "valueMac": {
              "type": "Buffer",
              "data": "Pdjv5GvooHbZi8FNXUbPVctqqlOnvaKVRT8QmLIybig="
            }
          },
          "xd9hsuVgX+CBr8fhSF4X9uer4MOXE85P4Kim7Pbhbxw=": {
            "valueMac": {
              "type": "Buffer",
              "data": "UQhOUTFQCKQJCcbzEcF8kjx7V/pbv3MNoytKAixJ1ZE="
            }
          },
          "IZrTPAXE3PHVRKsZDiyIA8FbSlR7fnIa2T+6G/ZCe4U=": {
            "valueMac": {
              "type": "Buffer",
              "data": "BWufljKPXdpENBIvxl8H75plz11ALCRyOnhRNmP+2cs="
            }
          },
          "iKKUJVyd7QwMU7CWrID+phB5ROv/v77e52XusdSc4l8=": {
            "valueMac": {
              "type": "Buffer",
              "data": "LeJCAi6GaJGBWKU2wdtV6hcF91ibiiTYBvDM60fV9Qo="
            }
          },
          "Ba8Ozff6mda8774A/fth42f3CNY76NtOtFCBVh/HfbI=": {
            "valueMac": {
              "type": "Buffer",
              "data": "a/7lDT4BuotKkGfoJGYUf1ghAi1NUYnDWBpaHv3Zx68="
            }
          },
          "uqodBTnLxfZ2KL6W6wVBSvDlMMcoyxt2rOYxZQPp5ug=": {
            "valueMac": {
              "type": "Buffer",
              "data": "JReNdNQoW1VF6OdT9VZHCsfradCtFXXC4ODm0tokepM="
            }
          },
          "/S0Aj9Ae0tel8qVtrQdTEToXMXA3Aeyk3gYUygyPtzs=": {
            "valueMac": {
              "type": "Buffer",
              "data": "PaHNHEYTcVgi1hqKhbykcP7RoaOBsjQgIbmdHfGNpfU="
            }
          },
          "df1DMPN7PtPYD/YSWFGyID136Ojqq+EX45DfDEU2/y8=": {
            "valueMac": {
              "type": "Buffer",
              "data": "l7c8J4yuUTv+bXCYCbuVsFATMhTeDD/4+DOvuX7UX44="
            }
          },
          "Xc0yeifZsH7t4zZmx0q7HZHr3QjYpt767zJjUsOwC20=": {
            "valueMac": {
              "type": "Buffer",
              "data": "/nrXTJXn7qnZibRrNtiqtnUui/oiBeSIWSQ/hZtpMeA="
            }
          },
          "ThQ1qdzPzWPx2wM222jhkVrcawniwKyyJlmrGK3M014=": {
            "valueMac": {
              "type": "Buffer",
              "data": "C8fCdnAJLYCr2XkIftqyh0jkhmHICjEX1IDX3vgRmdk="
            }
          },
          "5V6HI0eBR1N2TIuZ02gUkl+GuRhOqG+F7XF3g9nBw1M=": {
            "valueMac": {
              "type": "Buffer",
              "data": "uLbqKxPIgdqpNN7Ap+/xSjpYN9P954jAE4MvKLix4b4="
            }
          },
          "eXwYKZpMFboBDYGXMLWrioU8mv4BlZY+7gopaIHYGD4=": {
            "valueMac": {
              "type": "Buffer",
              "data": "Dh2vgbvOGDi2CDYyViOaOhJ3ZqT7Ve/Es/LA5pekOpg="
            }
          },
          "dXd1juHqKjIVQqb4RZ0YE2PJqYVlvvTV/RcWaUMlfAs=": {
            "valueMac": {
              "type": "Buffer",
              "data": "CH8j8CqrSlKDHDKMnHO5pH0rz9K/Ky/uu7b9xVz9zus="
            }
          },
          "mhjU696p+xCUcA4NE8TUOp/sgPNxbTAgDoCDlqFZ+rg=": {
            "valueMac": {
              "type": "Buffer",
              "data": "NtDXK5dcaXXbPEzoZfvn9ofnVdon9dsrgYxtlbkRYaY="
            }
          },
          "+aL9U9vad1Cmw2e5SEHPO9BFw3iM24boyh5+U0UdfF4=": {
            "valueMac": {
              "type": "Buffer",
              "data": "bJYGkGW3sXb+BfQzYTzEzQQlHiFpUUbNCI8zxWpdZQ4="
            }
          },
          "Z2Xj5R8HFB10fw00hgGlaONkmhMddKVklAkIUZkMbKI=": {
            "valueMac": {
              "type": "Buffer",
              "data": "hAejt9UHhiqq2dNvJtPHesgCUslHNHRhKYaoNk6//TQ="
            }
          },
          "djBl9HD7+GQKlONRNKY/zVYGl2k87aW3jxqGhRh9H/E=": {
            "valueMac": {
              "type": "Buffer",
              "data": "GSWDq7rCQ+7Iv9dgaKnEBVtt/9iPq9TrWIppemnLEAg="
            }
          },
          "tkMp+os9oN2Pr7CKDsG5/azoiOTqG1UCgBdZFFiQTas=": {
            "valueMac": {
              "type": "Buffer",
              "data": "7Dnjo7DFdqsFVp8Ge+f55QE5afshfpcdqe84RiUQmOU="
            }
          },
          "T7KBNSkH5W42EZjIId416blIEZpQOxAXYvrtveG0vAk=": {
            "valueMac": {
              "type": "Buffer",
              "data": "j9ENCeKd7LXV9L82VMeKcJj/kHMYmrX8FQLCaEFXtXk="
            }
          },
          "yS22GXN6mfKBLZ4A1CLWRbg6dqya7eRHJ4GXkQwJ5BU=": {
            "valueMac": {
              "type": "Buffer",
              "data": "U0BnIRzYxmg5Fb2OJ6a85B4/vVnWZSXPGq0m5pdXm2c="
            }
          },
          "SZ3QIpcfc45JgMLO7pIby4ZnqaV3v8+KYtTxKjoKGnI=": {
            "valueMac": {
              "type": "Buffer",
              "data": "NC+KMOGC6QUMjff7rKQRBK65lyohZnpIEuhvNAN1yKQ="
            }
          },
          "pFS8NO2C000ejfrBbvYxp9F1PaG94GSQxAidY00LAqo=": {
            "valueMac": {
              "type": "Buffer",
              "data": "CxtVXtJhf0xJ5QZYhgxB6WkmH7Say3XdUsnXjRtlaPY="
            }
          },
          "wNA0UmGFW4CYDlTiOWYim2Cex0uFbtSg8r1RnxRZ8MM=": {
            "valueMac": {
              "type": "Buffer",
              "data": "e/jp+cVuwH1/rVMIl/rI/UCMbDmGNb5p4A0y1PL5N8c="
            }
          },
          "6Fjm/fn58nwb8WsvmsCb4u12tjruw2sxiTN58FdwLjg=": {
            "valueMac": {
              "type": "Buffer",
              "data": "UfkMWqjltUXMe5Xqj1CsAL2WPGxRNheZdAObXBDrGwc="
            }
          },
          "oxe7o4wfDJiddEa/d03LLoqLN93COZDDHmhh+XpoLxc=": {
            "valueMac": {
              "type": "Buffer",
              "data": "7kVW/lg42bO7iRfu4zbwXTvr5p08icM8HYiKPXJi2Ac="
            }
          },
          "obs7gTETPq78QoLpVyK7mg9oyjcrZ4CU+9gdUJ27TP4=": {
            "valueMac": {
              "type": "Buffer",
              "data": "3YyQ2jxEQULj1tfqzVKzuSwRn7REYKntQTZIeFTOyg0="
            }
          },
          "0N6dPXYEHu04OgJ6rnJfehbfbelHLX/D/v52AZOhlvE=": {
            "valueMac": {
              "type": "Buffer",
              "data": "duXor057ATx+f5AGilfIuaLZLVnMXGuIYQp8a95EMZk="
            }
          },
          "1uK9OEZjFoNTYHVcZPOcHVdtenHIK3YZCN7t2g2xA80=": {
            "valueMac": {
              "type": "Buffer",
              "data": "lLYa4wnV+A/yE4kWIPKvs0dkt4MyNWvK7UHhZAAAtZM="
            }
          },
          "L317aL+rn9QXM79sGmEuFmzD56nhxlKmrCcmLPfr/6M=": {
            "valueMac": {
              "type": "Buffer",
              "data": "zLhrNNYkVaJoxsclPmwHtjxGnhHPg63Ixeemj+dG4Io="
            }
          },
          "buAf3d/IDpFk1vhw7meQeSHFqzwyCj7fvuGo7ykqDWY=": {
            "valueMac": {
              "type": "Buffer",
              "data": "+8yNwSeP5Y0XCWiEQXHvBLAY6RwbE4iemzox/XwOhzU="
            }
          },
          "JlgoTnneI+c58EDoUDaDeNNcrYIOzlZqcuRm86bm1Hc=": {
            "valueMac": {
              "type": "Buffer",
              "data": "Gw/zzDjA6tW0Ls6FisyVg744CiY7GC+zz3X7cp3fcpg="
            }
          },
          "4i9hOw3dkaEXt4mkPdlGqkBAajLAVJcslUDV4KjY4uk=": {
            "valueMac": {
              "type": "Buffer",
              "data": "QQ2nvnHLD4CquHExT9B/ixSVb5uOvuNhrdWiHbqACPU="
            }
          },
          "XjoT7VNlvMPOYfOWHXhG0hmD9bMla2rcs246szUzUCQ=": {
            "valueMac": {
              "type": "Buffer",
              "data": "s7Nt4kWBqer1vDNk0+w+XHWNo5ju8U2kh+dOC2VzqpM="
            }
          },
          "/3rSqtR8CT9K1MX998SPIV6sTGQnE48pEg21C4qLvAQ=": {
            "valueMac": {
              "type": "Buffer",
              "data": "CQrEMO+fTGWpcL3tSJky4aFqyN2JJP5oPHyV21LykHo="
            }
          },
          "AYGZyA6EkWyZjq0hFr1sHPnzaa62pcPJJd2O8KgPqWU=": {
            "valueMac": {
              "type": "Buffer",
              "data": "ZDefYcl4oNRPLFpRwiEcqVnuXFmz3lVaovXxPqqaYN8="
            }
          },
          "5GUzm9B/DaCsZ1EGsZ4K7pzg7hlYv1qls4mTaZQOdqY=": {
            "valueMac": {
              "type": "Buffer",
              "data": "qvTi0gXnQz5GwdxEsY86b662s//9dY8A4lc/1n6I2zc="
            }
          },
          "DexOJAW/Sj1vTNEtre4yUEvTgODl5h5w1WUoYzvt7GA=": {
            "valueMac": {
              "type": "Buffer",
              "data": "PL4ZNMKVckj/j+VZgawQSv5rbqzYMxMKFSmTJ1eOMh8="
            }
          },
          "Ik9pBKvlCn/Mrbuq2Mmna8gs0E7UhuXdbvLRNmsOg/8=": {
            "valueMac": {
              "type": "Buffer",
              "data": "1fSv8WHkZApWnsm8QhQ8SQBsU31MR4nTSLVFsXxjV1g="
            }
          },
          "WxEuDIniquaLPQhTZ5YAEItIRJxklDZnEC7cDtLvrEA=": {
            "valueMac": {
              "type": "Buffer",
              "data": "6ksxZGLgHACKJtOZZAqhHCpI39Y6boZNq1/uCVcrVIE="
            }
          },
          "Fwcy2ANeRY8H7rmscpQ6zNT311LWxmud67XxsAkfwag=": {
            "valueMac": {
              "type": "Buffer",
              "data": "t1/AGpxfAV8mKXfG40qxl51b89ik+bh0vOMW83zLNek="
            }
          },
          "JgW+SN9xWvUuUDQg0pTxkPBIj1EocM3gdBBW3Ngt3TY=": {
            "valueMac": {
              "type": "Buffer",
              "data": "NpeJp33PEgm7NSTLkC7TzULV2F4Y14T8iFjCKa+OplM="
            }
          },
          "CGC/3Mx3YMua/IbJoEjuZvlVI3kZRTrCmMFWjwrzDKg=": {
            "valueMac": {
              "type": "Buffer",
              "data": "sqGxsdtj23W6vIUPR1K3Z4f7MnCADON7T6cC+2Pm55c="
            }
          },
          "wpkdS2Ve5DayoWt44kv+1VCxoOLJfQSEgsRLr5cdgwg=": {
            "valueMac": {
              "type": "Buffer",
              "data": "79KsD3ubPQYqMFq4xetvl1dp1qh/dDkPL9cPACJEjTI="
            }
          },
          "y7YPCRiwaYolqvLegXSwjq8ipHfcg98lrm85I+JIgqk=": {
            "valueMac": {
              "type": "Buffer",
              "data": "fVU02OlyVq9NC4TvrSjey+KioZPyNC80nNGHNQ0vJ2g="
            }
          },
          "k4mL/kBpnCoxMaZETGBp60zdOJG6Z+ZWDFLNNilZ/ac=": {
            "valueMac": {
              "type": "Buffer",
              "data": "E6qcl/Gy4JfbORkhJyFhS3g44A52yQBDqXVIcVu2UYc="
            }
          },
          "JSu1IlLM6eu674QAUXKVvx7Zb9KT/0rqIx7U67X8T7M=": {
            "valueMac": {
              "type": "Buffer",
              "data": "5/o/odg607adi4SBVnnqfQ1IGHave8tyVkWCI7kmYk8="
            }
          },
          "NCSwXPTGzuMsn1kL9uFOkjGvpOjPmZyWQ1rnaOGVEbw=": {
            "valueMac": {
              "type": "Buffer",
              "data": "qIh0+LfTgSeHbkzTDaWUoK5MLqTSb1x3oP9C8uQTs1I="
            }
          },
          "xUL/6HnvDYrX8X2vqu8LrSiAN2ocO+ziF4IUX+e45yc=": {
            "valueMac": {
              "type": "Buffer",
              "data": "702+Aw830YOqsLygp/72BZ09KtCGwX7hKziSLnjoKPs="
            }
          },
          "fMYVKTZ2NpP4zatWbXN9K4I1fdJmB+ILprh8rxePD3s=": {
            "valueMac": {
              "type": "Buffer",
              "data": "lzROuxnRlNkEeBY8sYtG/zgmXJyONlh9551Woyy+hwg="
            }
          },
          "4hlXmu0eMf9TS/1Dg04PNiGqZhoyJ7YkjLpUooJP+K4=": {
            "valueMac": {
              "type": "Buffer",
              "data": "Fjwm+bbAsvD2OWZvjlpnUgcwPf1TcuYjDsA+yCdbn3c="
            }
          },
          "DRZam2fwVBINmQAlPLDG1XQ2qWD1rDZB8Lr6jjkrsHk=": {
            "valueMac": {
              "type": "Buffer",
              "data": "3qUTOcBpKkGwXiIGpkbFcBN5YxsT0Dj3TVLnrZSH3Xk="
            }
          },
          "Gc2f6lPcQ/0W4tebu0ID4Piqra8SyA3KDQEOngBDB7E=": {
            "valueMac": {
              "type": "Buffer",
              "data": "ZzBGaPSkVxXgqqi+hBCG4TnS9APMOY+J5rd7H09HJiU="
            }
          },
          "GYU2TvkcBimLw9j1kspJFSrBNw6Kp61W+ZzzfwiHKus=": {
            "valueMac": {
              "type": "Buffer",
              "data": "t2cGEQjfvizIh/ub3TyUeO5ClnKydYj5ifq3PhSmI4o="
            }
          },
          "jLn4JFux7lq+SwjoQWR0RmHcPhMo3MgE7bSHbJjKPUM=": {
            "valueMac": {
              "type": "Buffer",
              "data": "JP+F0wC9owqPOqyr9F4z7s/lZn6mIk+4M1B0WrS5F+8="
            }
          },
          "83/Jl7dqjmuabj2vb3N34TaqooVYe58jyxrlrVjTUf8=": {
            "valueMac": {
              "type": "Buffer",
              "data": "OZQQQgDEOhyt4j7HGD4RJHVhRh2dtIUQJxiDCMqE/TU="
            }
          },
          "UTEqxaSehMB3gYo1NWD+c2rHgi7u1nGHhBVWEfyHiiw=": {
            "valueMac": {
              "type": "Buffer",
              "data": "s7IUh2cOdBaFH7OpY9lvXns9Jx+5fL/Dtpunte3BFkM="
            }
          },
          "1/Zeg4EtT0Z4KmB7zgz/LNHvy0dXBD7JhjkvAEMUjZc=": {
            "valueMac": {
              "type": "Buffer",
              "data": "RZU3Ep802fOQXZm5i/eToJ7vRkXWQ60XX1IbFU63LPg="
            }
          },
          "LHFI70HcFgB13B/zr/hj1lnBtOlVX38+VKKGHrAqCOM=": {
            "valueMac": {
              "type": "Buffer",
              "data": "K+Nl0U9ROBNCruPr3yAsFeLlHodRYvNGnROL/H06HTA="
            }
          },
          "dkW9kXVDdi0TRAIQMa5CPMtRajhpYruAQDbGUHP2qHc=": {
            "valueMac": {
              "type": "Buffer",
              "data": "k5KNTdNhtNwREui7zQjfjwvkNS1y7IVar1NiG0wn120="
            }
          },
          "Ir1ywIoDog7LSVcxhci4/zczRdJYbSCKi8BbEiSo+HA=": {
            "valueMac": {
              "type": "Buffer",
              "data": "pmkumDVHgd9HnwXsneqypwYVarb3R5r7LTEOCVUz9OE="
            }
          },
          "iI5avitrVdunNXLKiMah9EdOwGCLAEpKGp9jc+PnXUI=": {
            "valueMac": {
              "type": "Buffer",
              "data": "fYTwK/uk4Wc2vufXsYUhW2tzGHZZWwWRSez4YyIM/10="
            }
          },
          "QZQm2ILaIpbzL8y5VrV9Ot41qPj2GsPlZ17LzsMGDAk=": {
            "valueMac": {
              "type": "Buffer",
              "data": "S/NhzqFSMOATE+yd/SreI6UWHJB2xCzORj02Eg8wdwM="
            }
          },
          "YolUTPBI4U1/m5Iy331t/UJhvnYkdBYEZsAIityb6jA=": {
            "valueMac": {
              "type": "Buffer",
              "data": "dmooJunk+JQA80s5KYyHW88O2yekm1qxs/wksWkTsQo="
            }
          },
          "wD+kR8c3giY1UxJDSWV2a5VwBSKjtQQyv3JxgsjrbF4=": {
            "valueMac": {
              "type": "Buffer",
              "data": "8DOn/lA9aFD0Tvq+Pl49mGqSpn97ztD0Aw35w6pI9po="
            }
          },
          "bDGEw6Px7sgHyQgYduYLLWolZp+T+dToeBa5IuA0Uuw=": {
            "valueMac": {
              "type": "Buffer",
              "data": "mWzIJ2V9HdZ6LR11E8/7N1dz6GklWlTHQDuO/y+Bgio="
            }
          },
          "wfU1JyB0m0tNDjaeDfuFGLzc7cxlYpypaUHDOJGWP0Y=": {
            "valueMac": {
              "type": "Buffer",
              "data": "XLN2vaVqXF8AEUVlqGdm5Tt6Dafb3HtHfUXsCjsKUyw="
            }
          },
          "O3mm8T7gG2A+36yCo/2Hh1g33o/BrwThZEgBxVCwxSM=": {
            "valueMac": {
              "type": "Buffer",
              "data": "IU4AP5Ib2lpCiYXRmH6OMqkjfEGRrVm6HqaMehIYtJc="
            }
          },
          "k3wbpuCPorSAkejzHVl+MEpPhpfxKPDsayIHyWtdHc8=": {
            "valueMac": {
              "type": "Buffer",
              "data": "SwQ5pSby4UTiRQn/3C/5dKkH/VkDqKrKkeIAdFPuVkA="
            }
          },
          "uOY88+oG+j6/EtT3CwBU7WqDZ5PSt6y0P7zh16C/LQo=": {
            "valueMac": {
              "type": "Buffer",
              "data": "Epvk9xXgKsL2uvro+Pm2QAPFXVWEahC0hrNzae4KYXk="
            }
          },
          "lBxcUMxqkCnfSgTqobp3VjcCYiADdcMJi0a7dk+SqOg=": {
            "valueMac": {
              "type": "Buffer",
              "data": "YxpKusJpJ8r8SCtP0jAyuq5Uwxj+wHNZcAo91/j0/78="
            }
          },
          "Cxu+jPztWHDj8VrVBMo8Azk6V9d4E0HrkZaAq/0AraM=": {
            "valueMac": {
              "type": "Buffer",
              "data": "kU9lq5xoNEL8xdf9x+AcNmdn9SmRTRR7GSYV4Uxq+CQ="
            }
          },
          "04yoTzDM5nVryjm3beOo8t5rOtKImf6qW69B0ZMyvfQ=": {
            "valueMac": {
              "type": "Buffer",
              "data": "SM8cye+G3WLSI6qLunOtSzRrd6Ql08mbS6stujaes2Y="
            }
          },
          "IjHVZSQO0K+vBCQYTRs8sqp5sPvJgbAR94VoTfkEc04=": {
            "valueMac": {
              "type": "Buffer",
              "data": "jpb/MspeyXO8Y8ZxYgKdBW4mQ1d0pB1mQEe3HTJ/lu0="
            }
          },
          "DsObNZpQBhijKKzXdsg5IaKGPa3GMhz78ZDyN7/dq3U=": {
            "valueMac": {
              "type": "Buffer",
              "data": "84EJw/b0GRwkZrRzSoLPlkvsrpNuyZi86GZP89LMr0Q="
            }
          },
          "y0yv2yMLiUlRSp8V63OqEUfHbWng7hCcrzfKZ7bcQbc=": {
            "valueMac": {
              "type": "Buffer",
              "data": "sR3uzSNeV8OLv1/zm6QABl7bDcZf5Zvj9hwa7cp2BeQ="
            }
          },
          "w1vVQi92ApeUSEF5A/ojXN/YpP8ix0e+rvQi7oIaA30=": {
            "valueMac": {
              "type": "Buffer",
              "data": "9i2/HZbm5iBrFbSMtc+3p9Br/C5VNx1xzk8swHVfwzw="
            }
          },
          "c67hiibnZAXxhbiA9cJz9MRRH5cd1DCO0QBm+ZUgwwk=": {
            "valueMac": {
              "type": "Buffer",
              "data": "OP6H/GM2jXqFstJmSTHI76d08v3hkq6Szeueekxm1ik="
            }
          },
          "DPdRQINCMNSseRr6LfM4go6H7fFyfsi8Mqo0UiIe7vg=": {
            "valueMac": {
              "type": "Buffer",
              "data": "lKMaOyGOMPaeJ8+FNy+j1eiwj9m/i1hjXnd6tYPEARE="
            }
          },
          "J1+S9E+AEmrcBumEEy2+V5tDmeOWnqbAKAPThTyubgU=": {
            "valueMac": {
              "type": "Buffer",
              "data": "+6qfosYKj2NNQKbbuxGjtJ6PNahKJwRYuODSPCY3TJM="
            }
          },
          "e0CrX1vh0mbaZKAPAnXsHZAE95n0z11zuwfrAxPHKaI=": {
            "valueMac": {
              "type": "Buffer",
              "data": "xKwo7bNJpePkrNkvMxqYQc7bDUV+lmiXUJNhWRDjojA="
            }
          },
          "mfmPG9l4ltw3s3xfEkcYEZspoJzop6COazf/2oYuC6U=": {
            "valueMac": {
              "type": "Buffer",
              "data": "MPqt35Vc90rcbUkvzOE9I94MOcvyMYzaplBZcFW/r5k="
            }
          },
          "EI1cHCTEPXU/5YjYp4UOWtp8wz93B7MN7XVLa9U4nrc=": {
            "valueMac": {
              "type": "Buffer",
              "data": "2pkumgbYze1QSq1HVWZxgUpyPgwoHty/bT26x5Q7Ro0="
            }
          },
          "C93MxOrJnbDpcSEnlrx35dozFNdv3//rKw/Cf24FPf8=": {
            "valueMac": {
              "type": "Buffer",
              "data": "ro0gGk6ZNYugf2yz/Z63abHIf6opoJkMTKttUDQY3Mk="
            }
          },
          "nvaTSN6EDibco0iV/biB7LkcsOIrWxtstRSTMrSoGEQ=": {
            "valueMac": {
              "type": "Buffer",
              "data": "t9dsi/TRUWHT/sg7oMncQ9RA31haF2XjMBeRS/dFoAY="
            }
          },
          "r4tx+CpB69C1Nnf84gVrCIJUwBcDmJohgjKKp/X6egs=": {
            "valueMac": {
              "type": "Buffer",
              "data": "O5Fys6ZZ4by7kQUDpY8yRXB1jmJMIa23tnc7/8uUMnM="
            }
          },
          "fLGfB5F84OitSz2G47GY2eRzDdkQidLP70hGK3H303I=": {
            "valueMac": {
              "type": "Buffer",
              "data": "2KftrFAgE6DL+TL5IPhOQi5rgR7u8mtjT+wecAkeTIw="
            }
          },
          "zh4VigHbpP06W/RDvyNTyHRB0hKxiLCof1o90cb8wVU=": {
            "valueMac": {
              "type": "Buffer",
              "data": "dtM+2lS5P31OMVRB4L6RUNlVcsFMGVp7h8hJRSBAQ9E="
            }
          },
          "G+KCq0imMxB8LDDttjsNM953qe36jHoV4dTiaQ59l/Q=": {
            "valueMac": {
              "type": "Buffer",
              "data": "hhbb7mP1CdxYaHm2upEA/z+g1LHC0WdiCFAFG5jLLEM="
            }
          },
          "16uhH1I0My+pDjndu3zLWeI4PYUpiHhYb2f8xGwh/Gc=": {
            "valueMac": {
              "type": "Buffer",
              "data": "ncEfCtK+X8hCDOoSHe6AEdal3o/TSLvvf5XBQZ8xzts="
            }
          },
          "lQHn9a0KyPJFxA6iLJxVNac/H+0logpKcfvqhdXAX3o=": {
            "valueMac": {
              "type": "Buffer",
              "data": "8k4x5N/x2iIe1M58vdfG36yDO18LMrzvfWcAwlXx2F8="
            }
          },
          "+KhNcc0+kZYnhRzL4KYbGd7QGOhlx2hRCiEfWfsNgQg=": {
            "valueMac": {
              "type": "Buffer",
              "data": "hkOJo+xb9JePnOmG6v5RuIfqUdWbjSshipiPCuVv2o8="
            }
          },
          "8JCAnIegtp7iAjEFhsYzbDKCftcwoKzO1T7nsWsWwkU=": {
            "valueMac": {
              "type": "Buffer",
              "data": "YealT2ca+9gk1OXuFPyRH7zcmph/ouByvEpCHvONX/c="
            }
          },
          "jhRK4lAZHWG8j43tswz3iA589lC49NZ/5UMN09cJ000=": {
            "valueMac": {
              "type": "Buffer",
              "data": "qHTETOiTnGr0rjMCxQy+MTCb/iLtuoOLzskUKXKC0Ws="
            }
          },
          "8909dTV5DYkpqG0IccDD/irV6RIKujHbqqxxRjzY90U=": {
            "valueMac": {
              "type": "Buffer",
              "data": "i7cssbPqRKqSQaPcVq5ss7dfGUO0O0ZuXb3uc9TAw14="
            }
          },
          "+l6bhydz13OQN8kkp4nnMSuHNtTnEaEz4v6VluDWERY=": {
            "valueMac": {
              "type": "Buffer",
              "data": "D5Nkb7MQHAKOiT92sJQhcQVNLi+vLX0HH4w0c9jCwng="
            }
          },
          "wEWad59f0yoGHK7fxVORJNMh/dBNFzOlCVhsEaYOOAk=": {
            "valueMac": {
              "type": "Buffer",
              "data": "vuoO5vlTM6Im3/+Sv2jE1rrO3uHTjRqrttPLXwwLH6Q="
            }
          },
          "TgRMdSPvWP5k4T0qL1AnBOI8Eo5XlmjVDdpVQ8YptA4=": {
            "valueMac": {
              "type": "Buffer",
              "data": "7/V2y+QbJIFx+hfLHrFD7Ha4CjnSZJn2a6KNdAzK3DY="
            }
          },
          "hP+mhiJucbeqxn696DnHJyNGAMp6m07OvaC4XFMXM/g=": {
            "valueMac": {
              "type": "Buffer",
              "data": "yDbj6J37X8a3hV7MdR6t1jSFgnRj2P19keo73EKbcLg="
            }
          },
          "yjC/v+2Z7ds7HnqyT7ITh5btI7SdVjTYtA1JKcsz5Kw=": {
            "valueMac": {
              "type": "Buffer",
              "data": "cIiCVS9RFpYC27x1ClSz5cPnFj6I9JmT3Q7/E9XKBtY="
            }
          },
          "d9GKYMdtXxTKgHNQ+ws4f3wddEtkZ2CYLiENGyA+XJc=": {
            "valueMac": {
              "type": "Buffer",
              "data": "9VlxLupkGV7GyISpIoleMeAdq9/quSBf295sF9QQS1E="
            }
          },
          "+SgnfEd/UVK5zIFbdQqjDF7qkkieEZJRj0/uIEZDvDE=": {
            "valueMac": {
              "type": "Buffer",
              "data": "MlxpqIZK+++Nmj6xegIEbcKiX3ziJ0i+Wcf/eXBkuEc="
            }
          },
          "QG9U14a2Ryy+8bq107lCJS3ZDYTPTpC0j78U8AHrpzk=": {
            "valueMac": {
              "type": "Buffer",
              "data": "e7XbihIQaxFNoMWTstbWQO06Zl5stkN1tSQpGtM9vtY="
            }
          },
          "g8Rz7/QsTwNefiWr/grM08j93Hf/U5aejtXmXBPvXlc=": {
            "valueMac": {
              "type": "Buffer",
              "data": "pLZ+VXhaUahThkIFx3pTH1TuZXZDiUPF9mVtJxGMNtw="
            }
          },
          "xu5UTHCtM/8tAfbrlonGcVZNrP0JIznnD/c6QmrWbBg=": {
            "valueMac": {
              "type": "Buffer",
              "data": "WFlvtJHHRZ0WTcTEvvYArK6l6NV2/nh6p+SG1PtUY4Q="
            }
          },
          "gWgvLCq/+RkHZNkMKiCpP0T1AkMkvOX3yPOpiTgzeuc=": {
            "valueMac": {
              "type": "Buffer",
              "data": "mSiySCitVNp+h6Z1uiHHAtIAd4eo/pcj2Ub6tiMT7/c="
            }
          },
          "VBlMY6ZzONTykbc46u5OVzI8qaL0Nw+xeyyl7vJk4C0=": {
            "valueMac": {
              "type": "Buffer",
              "data": "U6ivAW3jDby+02OzOa87q/baHiQWaYPthhaJ2crGe+Q="
            }
          },
          "REVbtoNV4+ObWjWP8gIgpr38EW3mDniDjjSOdTcgnA8=": {
            "valueMac": {
              "type": "Buffer",
              "data": "v2fJn+DfOPXOLphAYuPn0GV/bP7yMc4zNut4kxdbCnc="
            }
          },
          "TWldImzL7t3Bai00v267ldSWfJ9BbLjdj+X7mJuUAXw=": {
            "valueMac": {
              "type": "Buffer",
              "data": "fwr8/+ZyFYCaAPMi0YbQGfrHeSiKV4pG9nqVGI5N5Xw="
            }
          },
          "fM4ruYHe6DNfAmgypRjXKpiat20oKuJT/wBKffz60MM=": {
            "valueMac": {
              "type": "Buffer",
              "data": "2CjjGS4CMWz2c96upbtfyzi5hO9BH7YM0Se7IcuFges="
            }
          },
          "p6Mlp4vf3+YO3Ryfx85K4K9oVmrldne2ZoPlx/XvUjc=": {
            "valueMac": {
              "type": "Buffer",
              "data": "aUAWYrDYCT/y/zVkWW0mEXec4Vj23vFGfpSD1/FgQuc="
            }
          },
          "fC54CrmQ5KWjyIYunkh6aLaxrfCTadt86hJx7z/v34E=": {
            "valueMac": {
              "type": "Buffer",
              "data": "WQXRUhhRWxxqpWNt601/a8v+aI0mC66Kl/Tcg1VMEps="
            }
          },
          "v5KllPHpo29EeVdZzC57O5qigjP8vM3zuTUYdq9wC7Q=": {
            "valueMac": {
              "type": "Buffer",
              "data": "7adgyt4gbsxXWskm3zR5Z4Q/aqxGGxi1nzzfKsOi30o="
            }
          },
          "gvbwMJnzyEaPg7+xJs673X6guXrMMOs1umcDtuotR+Q=": {
            "valueMac": {
              "type": "Buffer",
              "data": "8OPlNP20P8Lyq3ttIzv7oPX1RhoIpUUcu+R+02FY0X4="
            }
          },
          "5n7Ovj+mK1k3nzqTJtfWKPtHV3uFjauUEpm11w/V7Ws=": {
            "valueMac": {
              "type": "Buffer",
              "data": "uMnOoSezKo9ISEuC1oIf71CHKKHlqLyVheB5XJwJhFc="
            }
          },
          "8KNgGKONNFIq0h0BI1nS6d+RQRcLMT57/OTyAb/0JNY=": {
            "valueMac": {
              "type": "Buffer",
              "data": "FLwtAFp35QUyYMt0xtLUe4gDQTKhIw0hbsuzGZsNGG4="
            }
          },
          "In2eQk4gokkd2idR/l5pdrlSioTacN69ziIov/N7uV4=": {
            "valueMac": {
              "type": "Buffer",
              "data": "DOD4I1fg8SZRrNhXzMwaT0ApH8dYH967ytHW91upq7A="
            }
          },
          "Vu2wFTpZDelK7O7j5pcgxpzOj66zAcMMRgHyLyK99qo=": {
            "valueMac": {
              "type": "Buffer",
              "data": "Yfw+y71RjThjzMCAJXo/D9a+V89xA9Y9d7h1/7JWHI4="
            }
          },
          "LC8wqUI3z5RhGMTjmno94NZZo4Ok7/YLFOoNaTcQE6Y=": {
            "valueMac": {
              "type": "Buffer",
              "data": "oewojW3Rjd0doF/X7TAts61xHEgTmSScZGsZrGuPf44="
            }
          },
          "ClLfl+b7uNUv4RfHC6ETWWnVswnDr3vpx1Qqr05XxPA=": {
            "valueMac": {
              "type": "Buffer",
              "data": "0IjLYTPkkQTXd/IZhQeiqWtBb1mGXMGR9JoPkQy98UI="
            }
          },
          "UHFrpq/k/mAc/3VYmiW13NQVTH5u0eLPWtNIpd1w30k=": {
            "valueMac": {
              "type": "Buffer",
              "data": "Kxgx+FYPAjRqYdsbFFqBuE57XVK4qrx+7/CBJV2cvec="
            }
          },
          "UQa0DHWzvNz1GPBnHzQ49ZKBO5dqU0S6s1SYSEPo+z8=": {
            "valueMac": {
              "type": "Buffer",
              "data": "gpr5ZiHkOlqNDCtcXMvDHnkXEXzlkbg3Dd4eW25NqJ0="
            }
          },
          "DInVCQfNJzRD+qyDpWR8epg8Hpva6MMETmQop/ldll8=": {
            "valueMac": {
              "type": "Buffer",
              "data": "FidmVx/NQSSHL6DxtXSIN8j1pjPc7FlfgZwkfZ6PpOc="
            }
          },
          "NIM3oiG9TzrHvmOdZEc7iF67JBOyeYl6isvDxoNa/zA=": {
            "valueMac": {
              "type": "Buffer",
              "data": "EIjtrILqzLFzCMUoi4pktZizM0wVB0Pr0KtsUf+4mwM="
            }
          },
          "ELaCucLX19ABTVSTov/NjyOwoj3NVWkwDvjhvMUZFAM=": {
            "valueMac": {
              "type": "Buffer",
              "data": "FP4tcIMYdCQv3p/0X7qUYYHnSTeeqGWgTq+H5gqb42w="
            }
          },
          "UZYWUcyHwIT46v6ml8ri6RfrIAGpVyRsSb/99pY6dI0=": {
            "valueMac": {
              "type": "Buffer",
              "data": "ew0XSBDVSIHBx4Ixib4SL3Vxua4FqRYqdRGBzmlvxWs="
            }
          },
          "0MhSn7VQAsi3tm2dwaKmB6lQVhRxH1YF6NknCUiUZ2o=": {
            "valueMac": {
              "type": "Buffer",
              "data": "wzGBrKPIlX3DTWCsaT94eJKIjoHRHrHj5W3e4nkdNHI="
            }
          },
          "gIfKNkfbppvDAIEnGXazrGrE/ooJypnc/Ilq6clDGEI=": {
            "valueMac": {
              "type": "Buffer",
              "data": "ky7ihWskIMaie7eeTwhl8OLidp/bTMFnl/7B35CTwFA="
            }
          },
          "moUoHCA1Iq5DTdDDpkwgR9Q+iu139yss/pxAHAa3Wnw=": {
            "valueMac": {
              "type": "Buffer",
              "data": "VfUIIVxpeiTJ6ZTaGB58uQ/oqji3/6uVit2fiaqzric="
            }
          },
          "O7JIXHUA5L04pwjeKwqH6LTyYlmK+xxUQT08iBiR14s=": {
            "valueMac": {
              "type": "Buffer",
              "data": "nAv/oFINtoA7rJkA2x8k5DXg3ZAKikUc9fThoOrl264="
            }
          },
          "cMbJ8YYzthPP9ozhGmB8VVPh2Rw8WfQp/j3V33oOMVg=": {
            "valueMac": {
              "type": "Buffer",
              "data": "N51Zj7RO+apbiMKNNWhfWflmLz13UEcOZg1R+8ZZyBE="
            }
          },
          "u15YGRFZHnyZhJJIYLkwW6MLsvf6426uWQJX/tPLtfI=": {
            "valueMac": {
              "type": "Buffer",
              "data": "//owt3OKz1X797P9Go0MThcO8LlSNNz3aIENAXEBI3E="
            }
          },
          "jy96W24kf1auNELaaEE0s76Nf2LQ7ILY18zliILahu8=": {
            "valueMac": {
              "type": "Buffer",
              "data": "hdbIoehJm5cOH+jPnuPcabpzYORzw3IhVikUTKbPF30="
            }
          },
          "OguCbFSs+++NHTxr5mUF5d3z7VC7ClUkpqSfNB2YVQw=": {
            "valueMac": {
              "type": "Buffer",
              "data": "ppONEyIK1mYvBu4RvKDyTq0CP5AIZNKfpbQZgx4AkCM="
            }
          },
          "IOewsDkUhgre8LvMWtF2CFiumjZTaN29qmCp58LlEog=": {
            "valueMac": {
              "type": "Buffer",
              "data": "ZKV90gHhmVphfoltpKYui7CiMGDG9yIyz2ajnXjg+Y0="
            }
          },
          "JxtSbaoe+FeoggHATaB7WM1R6Ox2GNkNV4MYgYIlyAg=": {
            "valueMac": {
              "type": "Buffer",
              "data": "pSZw127m/+HQPkCdNtyG9klojTEw6rnvLTdECHDnQ/8="
            }
          },
          "vvygO/9RYEK0CmUMBJgPbyX8ipxUiW7hNWpCbWpKrGs=": {
            "valueMac": {
              "type": "Buffer",
              "data": "36HI3NyVgurrmrGwaCKSBpA+3LK6lT2yk1OSiRm7A6E="
            }
          },
          "UDULzXPGIat1jU/CVjl+HI8KI/LfaGFQ/hQ2cI57Bl8=": {
            "valueMac": {
              "type": "Buffer",
              "data": "hOUKOt3DLf+sHqxK8CXGk85o99iIbybI+N8xwdgyIHY="
            }
          },
          "R09wlYF6a3SxjP/M3fgRT7x3+MIDRdYbni+LsYfWhEo=": {
            "valueMac": {
              "type": "Buffer",
              "data": "74tHb07F3wmZFQlYwdp+6LwNWmiBU5BcKEKemHh4Eaw="
            }
          },
          "Bv3r10upiucAsZZ6bHpZDHb1cLqdSSkykdFuvbBjjIo=": {
            "valueMac": {
              "type": "Buffer",
              "data": "lVxl3tvOURfpIXkZrhiVkSfKj3uiGe+IGrk1QaLtfAs="
            }
          },
          "/PoSauAs3NFGGtkLdl7Ng8Zu4a1SXpKSlsfzqyeIc0E=": {
            "valueMac": {
              "type": "Buffer",
              "data": "nbSeQ28cPxjjWW7i+lBBqsOZoNCxnWte5XO33zIZq3g="
            }
          },
          "WBI2MZ5M6bAH8TDlj1s/3V9i3pULC2pN56eimttrDxg=": {
            "valueMac": {
              "type": "Buffer",
              "data": "ftc1s7aCx+pCpg2TUJj3tRMyivdsgEWCTCqQltkEaC4="
            }
          },
          "KqEjNU02Rm9cMQ27vgecTKhXMQisRIWDFCBZnkJMxN8=": {
            "valueMac": {
              "type": "Buffer",
              "data": "znmZVUGSHi4UUY+tlbPpDLPu9DlFjHwCCKWu69THNcI="
            }
          },
          "OTSfpQJ8cjhJEv2POqqPk3PUgYMoMwyHjQQnCaxcQYc=": {
            "valueMac": {
              "type": "Buffer",
              "data": "U4729zTb35NF7ZPbiTVACVfw84UMuHIiDm3dmrERZoY="
            }
          },
          "JSbdkPewAiup5S5ATZtnvinCpeHVkP3l3A8PYkK8638=": {
            "valueMac": {
              "type": "Buffer",
              "data": "31ATWkhX2Nvq4aUWzL1bRF++6aGAtFIss+K9XpcZ1YY="
            }
          },
          "9Po8wetexQUjVEn5qU3amuUoNSfvGpAO4XXtXLEfBc4=": {
            "valueMac": {
              "type": "Buffer",
              "data": "WFnja3+V0AqbNbto+a7gNCHDFC4FE5G0fuCczSeDpMQ="
            }
          },
          "KYZUIAuarL6rKxNJ3qE6di+1t0aBPhdUaCObnNWFrQA=": {
            "valueMac": {
              "type": "Buffer",
              "data": "eVJerybQpZBTwZLOfHCkEdl8oVYnSWHMCdPjJx7Vsz4="
            }
          },
          "P0tRRC+TNg/UxatnJr28nk1nH5mTctYLi0BfdqUctT4=": {
            "valueMac": {
              "type": "Buffer",
              "data": "AVNBqT7kSna22K8bYxtl10j3YFGTJ6qUJCP1cubNIZg="
            }
          },
          "EYySWGAM3Uxs/NR5QhAB3Y8TMyCwbxCaBY2OnGux5O8=": {
            "valueMac": {
              "type": "Buffer",
              "data": "cegZqjfRCpPLbgDbV9CdQ0Wo0w0jxUpDlhvSYFlUYzY="
            }
          },
          "hxdEmjLo3aa/z0T+CBXVdU9hXOUdZsqSUcmCFXc/8wg=": {
            "valueMac": {
              "type": "Buffer",
              "data": "XhwTfTFkO/ZaoBXIRU3l8PsW45YMGIN+69TXC5OIN14="
            }
          },
          "N4rXCJmtUWhsmJXdpQjkK16jKQuZIT6EFMInG8bIJec=": {
            "valueMac": {
              "type": "Buffer",
              "data": "rzSplHWIkNToP04iW+Q+vKbYrXxB7h/UfWetMJAlV4A="
            }
          },
          "/O2YZJqr/it647aTvHatIR8w18HmnT6fy7fqZTEANZU=": {
            "valueMac": {
              "type": "Buffer",
              "data": "mbW1r3drmsVupkJesrDy0UYZIKT4R2n2eWY3/X0b7gM="
            }
          },
          "v4LiD3fpf1ecrI2s4N4FUhcJQHwJwcF8CsI+8XX/eSM=": {
            "valueMac": {
              "type": "Buffer",
              "data": "pepAgbbvixl1ES5VRUuezOBtjDOLnteTVtWkM76T3X0="
            }
          },
          "y/d4b3dhP+Z/GP6FBoIqelA10g46b12V/GPpzA9FkX8=": {
            "valueMac": {
              "type": "Buffer",
              "data": "mmF/kYjTPgvtFciVb3b3N/ZTmqsjpjYKbP9u7a3LOsY="
            }
          },
          "6OPOVN8o1/RrfjeeNYHO5oaPgMKHhl5rHzUoTDc+eHo=": {
            "valueMac": {
              "type": "Buffer",
              "data": "l/rlG9JfR4lCMsK+BsSGZ5pev6WaLu5AnKvboMGFdrQ="
            }
          },
          "aBM4rOfiDfTKZAryJy0aetB5K97/MqxVxw+RvZQVobg=": {
            "valueMac": {
              "type": "Buffer",
              "data": "MJxWXUXZU96y2IWBgg/hGdCPMVTrUESRTanSsdtcnnw="
            }
          },
          "167WsVWibxTHKR3UHveUvUa5duWtH070Cvfqcy4nPS0=": {
            "valueMac": {
              "type": "Buffer",
              "data": "UgrDbuMkxn/1plPKVROHmO1I/Wwbjg39PkbYEN9kYik="
            }
          },
          "v0wfiMdBld53aSz79s43s3/WBYMAcmA2IxhavCpEuVI=": {
            "valueMac": {
              "type": "Buffer",
              "data": "5+dqoUY5LCMP3hy5APNp+mpsy6QFBxM1mb45jEDaXFg="
            }
          },
          "FchqS/CBvD1NAxh/DZUKzjOoHJIlgpaGjD54MXWuvWk=": {
            "valueMac": {
              "type": "Buffer",
              "data": "bpaG2AHCkFyCjm5TLj+GimddYpI0A4NJeeSyoRpE/To="
            }
          },
          "piPeGnn1LtcagxOcgrd5roadsUqiPn89qdzOChhr1BU=": {
            "valueMac": {
              "type": "Buffer",
              "data": "96Xzy2XOrZv/6h80xwegHVlieCjy3Gqy5K14f90lGGs="
            }
          },
          "RJyMbVN6Z5j0CHJLdDayhfsuSdHgnMrw89EY7hehqbY=": {
            "valueMac": {
              "type": "Buffer",
              "data": "R8QlYqGWsqP9WrYh89wtq0sDWmQSJS/RcTVz0VOuWDY="
            }
          },
          "sscCpttiI8Z+dNqjveufF+3WzvsrphmxjQHwPazjC3A=": {
            "valueMac": {
              "type": "Buffer",
              "data": "az/ZiX9rKRqrkWDRRHglmHr1Ud4cMDy6Z90TcKvp1QU="
            }
          },
          "NBJmD0uyt1yu/jE2Y0avudigi+vLVnA0pr4vg/52LyQ=": {
            "valueMac": {
              "type": "Buffer",
              "data": "ziRvGk8N55jphE19jxDvalQljpSfLbfCiWWJMIqyM0Y="
            }
          },
          "X/mZMRGAMeTZWx/8LbZyN7Y07ywiUeo5jdAzYJQLfSQ=": {
            "valueMac": {
              "type": "Buffer",
              "data": "lcN9rc4NpmPHpwm8nCD2hyvhCBorIfYFW6YNvWyjjXE="
            }
          },
          "2q+meE64QjQtHXlck8AT4BioS+PEBA3fhU4r47NlgDI=": {
            "valueMac": {
              "type": "Buffer",
              "data": "WNa6YqjgyyCIC6AMYcUKClHS/FneJk5SvqZEjzjNsHk="
            }
          },
          "22KnlfqRj9FjOKwGDu6fWMp9gLnSd5jfxOre+X8OXeM=": {
            "valueMac": {
              "type": "Buffer",
              "data": "RMxdjDLJlBduH+uMX3Y5jh3yvxhcntAz9gObghLaD/8="
            }
          },
          "5o34yz6S9PBpa1uGKEhHCrON4/jh/BBOVrnYmLtdUGI=": {
            "valueMac": {
              "type": "Buffer",
              "data": "WkhyYX+eUGUsQL/SokRsAprx02l6Di5b1CNSY5I4bFw="
            }
          },
          "9R7KMJapvn9y/2van9fWHQH+FOoGaot0/38ptFPo25c=": {
            "valueMac": {
              "type": "Buffer",
              "data": "lnBydglnwxPKrFlPiTkh3lT0Mr+F0xgLjkDs1abt2wY="
            }
          },
          "Lx147JyJH7rCzA69ywAKVJ6rRjAJB5xlkX2gEfA/Fbo=": {
            "valueMac": {
              "type": "Buffer",
              "data": "w0DSu/sv6MKa+Clc510SCa81/gF/6R04PpCKfCNR/gQ="
            }
          },
          "oRfBW/xx5hnmUk6FLR5midzjYqQzHMidbio4rcVuwdo=": {
            "valueMac": {
              "type": "Buffer",
              "data": "l5qXlCypjWFVtkAortZz7jAULdV+drJnWFe4YWFvczI="
            }
          },
          "w3jTdQ4ziCIEHhquZs7zbpUefjIHXjqApRn4kaHs7TQ=": {
            "valueMac": {
              "type": "Buffer",
              "data": "Pw38xhhlIjbcE7jR/lpLiiOheDv4/mAoRUo2lNuI+3w="
            }
          },
          "hfq+h1vg9u457V15zG3KAHAWV3UXZhC5HqM1u/6JO9A=": {
            "valueMac": {
              "type": "Buffer",
              "data": "9JIhb14dIXcsNwR9KFt7j8ottBBAjEoGBzjp8XDVImQ="
            }
          },
          "snyvs1ETk2f7NiFhDLkvfdtSN1dYEI9zDHmAlbK19+w=": {
            "valueMac": {
              "type": "Buffer",
              "data": "R0eU1YNfc/03UmChnIT9vdVNCxtkhvzsow8bfMIwJ5U="
            }
          },
          "U2cyKnI7hahsyrgnEiXQ7RmB7XwPISf/KKVW4nErrgM=": {
            "valueMac": {
              "type": "Buffer",
              "data": "5IwwjdhPGVydEwM1qfeGjICXRGlsP3SouO4YhosMx3U="
            }
          },
          "pFWvjS352XOcNucEpchUkY7TsdMnWAAYKIEJeU/z6SM=": {
            "valueMac": {
              "type": "Buffer",
              "data": "lExxWxGzCV6IpbaYVMFj0antQbMhtavrHqOwO5/LmiE="
            }
          },
          "x8umy93SWmzhMkBRSvxxgTJntrTwWnhnKccHG5makY0=": {
            "valueMac": {
              "type": "Buffer",
              "data": "iaAhZEJxGMEgXDwpXA6eQHpZK8XMlbDj7u6KwQpQznE="
            }
          },
          "aoe51LJMfQRlOhHQi4aT/WOgk2vFX65PhyPi2u0H6uE=": {
            "valueMac": {
              "type": "Buffer",
              "data": "GX3qy+rEMkSpHoHA83FWbPRtEw9914kdJjxIAnIlTP8="
            }
          },
          "y8ThMPfW2F1qi3RGTqYqcd3+GyWHqEs9ZKLnIICfJko=": {
            "valueMac": {
              "type": "Buffer",
              "data": "HnksF/6jnNs8w84UVj69Dxsh2o4ya0EGA0FS1x7pu78="
            }
          },
          "86zMfROsQRK7EcNDgrsVyQUsTpBvjPGRz9NEAh7T2i4=": {
            "valueMac": {
              "type": "Buffer",
              "data": "zHGaXtSd4DuS0e5zD8KTUX7dc+XrdxVuXV3X1ul40TU="
            }
          },
          "2RzDr6niUevkwteEMvY55OfPJei6D1IuskoDBRhECTo=": {
            "valueMac": {
              "type": "Buffer",
              "data": "eZJG577TBGVoEXKLdJNyNXLSZGqG3VhnGNGp+WwhkOs="
            }
          },
          "cZsJ7CaHS5dDJJJy3pCfrYc0HvXtst9KfsDxwA2LBH4=": {
            "valueMac": {
              "type": "Buffer",
              "data": "1kJZhL0E5hNqWC+2fz9xO8pHucQk3tK8onQhxFMPsWE="
            }
          },
          "Uci1i/UNVrvg81bANmQ9kxMRaJ1v1XqevcK+Dyvldv4=": {
            "valueMac": {
              "type": "Buffer",
              "data": "fnbg1U4Cw1ZAA/ivLe0e3FHdQgsAKYv/q5ErjwnO8YY="
            }
          },
          "g7QYqceP0wHaVbVUK/9fFxfAeWDgeXGdpijIRPuooSs=": {
            "valueMac": {
              "type": "Buffer",
              "data": "8OxTOaaoW7fJESnfaKvSVP7Vzkc17ZwI01Ecd/x2alA="
            }
          },
          "9U3Bn4nno5GJIHHP4NZ0M4iV0BhVH2kNI6TNyn4ptg0=": {
            "valueMac": {
              "type": "Buffer",
              "data": "MxKek9lqIsO7QtfW9EhqNOD1fNdOJJaYpO6cT7AmGJU="
            }
          },
          "tnkvKkvykzcROUhjiiv5gwvQE3AMalsI1m1hbAU3XWc=": {
            "valueMac": {
              "type": "Buffer",
              "data": "OOSgtFHTmioR59HVEKJtvOEbj1br3eauQumFdNPUlFE="
            }
          },
          "tPo9YTKy31vDYYboF9R70/2iGuJ8w85r8t/PDCcz8cg=": {
            "valueMac": {
              "type": "Buffer",
              "data": "ZHjTha7VnvjESXAIwuXgQb0cF9gVWMIq4+bguTVkDig="
            }
          },
          "PkfpNUBVZ33O8DGId47wqwtOY8wDmq1nSHe+Of2jhOU=": {
            "valueMac": {
              "type": "Buffer",
              "data": "yxulBzqDzU9EIEi+o19Phd44pdVZXWdCknmwqz2Xxxw="
            }
          },
          "ZYrLT7Xz4fU5XAoj0vjTEdQqOBRt8k2ELBaai008w7Q=": {
            "valueMac": {
              "type": "Buffer",
              "data": "lExAa+Lrj1LA8UVh0Oa3wZHwTnKLMi05Toz56CNEA5A="
            }
          },
          "X0I7G1hWXnjgMYfj6mGkmdHlvdEODhqEGs5TvoCS5M8=": {
            "valueMac": {
              "type": "Buffer",
              "data": "YTrg1WOfI7BWUypABXuVXVLIhkdMe0pGGnZAEpauvpU="
            }
          },
          "m+DPvmNgDTKJUWzrC7GfoPcFcuyAI1vscQUYAh5Angc=": {
            "valueMac": {
              "type": "Buffer",
              "data": "tYkIYNPFDHob/hzyQEVz4e12FRj/n2q52PibSZ3UmJk="
            }
          },
          "i1JdA+ddudTU1fL/CDD9VmDdPITGTqOZwuEycsY6UOc=": {
            "valueMac": {
              "type": "Buffer",
              "data": "OZFc3JtmP/WEt+cb+6izbS+jqg7KIQK/ZCNPfHq14XA="
            }
          },
          "+G1KfdeRQYTgTRFTuddS1zugZYXnEEZz59mkVnin81Y=": {
            "valueMac": {
              "type": "Buffer",
              "data": "eMFH9gW4ssCERr+wPM7B0xDi1IBXrRa5XPuHajdiEds="
            }
          },
          "Dt/VJOD0uyDQZuV4NPFQ/vw6c9sP/h+8HI3TwEe3ecU=": {
            "valueMac": {
              "type": "Buffer",
              "data": "omhVF7o/FS/Q+y2tGItM26M4FsMvsP4ECx5ZURZeGmc="
            }
          },
          "QkvjD/ueQWKOK92ikQRvjDhG9eZyL0mI2ylVaPfR9Nk=": {
            "valueMac": {
              "type": "Buffer",
              "data": "slQPkAFMPL6mVYl3QENdSyMpff3vPHD2IbAKKF61vtU="
            }
          },
          "VC1s8kpk4wtkLRUerm4ERRPiFS3enpez1y9VySW6Htg=": {
            "valueMac": {
              "type": "Buffer",
              "data": "IsJe/SCv0CEGIMmlRUStllULcg+/d41VJ819XBruqEw="
            }
          },
          "jp3YTr1Z76PN5xorfrov3q4i3v8YVH8zKvNHz/tQtyo=": {
            "valueMac": {
              "type": "Buffer",
              "data": "fIUBXpQh3EUs8ynf/MU/C3Q5WbLfjJy5MF/CFQkiHRI="
            }
          },
          "T2RjlY0hfzkz/q+2P1BfcW4eLCY6jgJZldg00z2Rd9c=": {
            "valueMac": {
              "type": "Buffer",
              "data": "qhpoo/bgnxIOpEffpvxCChbPepvu95Pz61UWqe6H2VE="
            }
          },
          "NxDUk52t1DP34eY+meTp7m6VKYnwXChzN8jv/xpgvKc=": {
            "valueMac": {
              "type": "Buffer",
              "data": "/xaZ+hcyzCQNuyu8vOZcMZmQS52ciCntKaJCi8ktplM="
            }
          },
          "2LAYCwkjr6hDIdEMYLfbyxsG+4i9OAsM2CJhabXXgzk=": {
            "valueMac": {
              "type": "Buffer",
              "data": "mzO5D4Rw6m2ewFuewkzixH4vV/EjwlqZhgbAGnnoiV8="
            }
          },
          "ieN4TmqyTTsj7EXnZCglpwZIujleTqTBhoEFh+VgurU=": {
            "valueMac": {
              "type": "Buffer",
              "data": "b3Wwt6wnkZ6JtEUOL6eig1i1wEbQmbN1rdkEHeww3XY="
            }
          },
          "oxD3GPKUw1OyTC5icQ4OoTqhVkxxye/rr1kiIJGz554=": {
            "valueMac": {
              "type": "Buffer",
              "data": "t4tVJapgnvVbvARGmOLM+TgvT5C0iai5/e6L1H+jDPM="
            }
          },
          "fWcXO8KXtaKAF6ROkiOUKaGLnC8AzBkiAgf7p+DrxrI=": {
            "valueMac": {
              "type": "Buffer",
              "data": "tVkxypjipUFOHH7JhHia8llOVt2RP8KbRyxJ1OXFS1Y="
            }
          },
          "bUWRVgkks4zOI5BdZ1C9xqhwNxukZoc7mAbIxx87LF4=": {
            "valueMac": {
              "type": "Buffer",
              "data": "o4Rlr75qjNcLWnh7m60lklUO5XU+SGc64ua1seRIQBI="
            }
          },
          "A0Y1H5VrZtkvyNgUNVDM/Q01TOTTTikn/N9cYwvUEGI=": {
            "valueMac": {
              "type": "Buffer",
              "data": "/byqG3PoWCBcNWq9HNiR1kqhC2O9Hgsoki2/jFsXOO8="
            }
          },
          "LcOzhRoPenQdQBcEmt7p7SoE0pRhYOsYY+qPkwlSoN8=": {
            "valueMac": {
              "type": "Buffer",
              "data": "vHWG2P2lZrZSbMk0klqxc2gDAGWYXLOnUEzzvAYenVE="
            }
          },
          "Hnu89sAFHsfqbW0GfHWs/OV60F66DuHO7qNYX24nwMw=": {
            "valueMac": {
              "type": "Buffer",
              "data": "HmDk7BiupLOklYGZIC3dfc/GoftyU01c0MdQWhwKKtY="
            }
          },
          "QhvDGSckAe5MwdKfSIWtr5xOj8jMEksmccTjcmqWhks=": {
            "valueMac": {
              "type": "Buffer",
              "data": "M8Pe5IZAE3qNCAMVa7itFvir5KkW8p2TNO5MYWg0MKo="
            }
          },
          "7ij+SiMH5lvKPLMaG7hlt3BL6rFvStCMvpW/VbSd3bk=": {
            "valueMac": {
              "type": "Buffer",
              "data": "2C9SeWvhUqWznzUCa+35EEvW/VKgSIKCgWMjzXPXXEI="
            }
          },
          "/A99L9Y7JSLGF6+QRhd9cq55m01FRRNUDhIspiH10qU=": {
            "valueMac": {
              "type": "Buffer",
              "data": "BCYeUKt8/bR/lnAuTWZqeiunIbI1C53N7fGan7TRZ5c="
            }
          },
          "6dd7x7HZYMeyeeg65C6lGDKWiXpILOXaBBr8xgADJUE=": {
            "valueMac": {
              "type": "Buffer",
              "data": "l4BWvzs6mdKlthGxI1fC2TsMYiNIYpacd6T1+bwjj1A="
            }
          },
          "5DreXeeCBC1fjYHO+sP/SzTOE9uBm+I5HojOL10qQbY=": {
            "valueMac": {
              "type": "Buffer",
              "data": "KcHpVT8OdddjPXaTCOYumODn74WM7xZKRCR0ceSl9ow="
            }
          },
          "e9brXVUqp9hrvMZxS1/1zj3AlJA0YjnaC9KRkhxsLU0=": {
            "valueMac": {
              "type": "Buffer",
              "data": "Q1Yp3xhlfbSxbBkcZwB+j8yoiWxE5kQjtV6NJJnYU9o="
            }
          },
          "ZKTKlRqXNGS+zsMiNJt9Ih32GDUuZ/2dHyKCgDq8UB0=": {
            "valueMac": {
              "type": "Buffer",
              "data": "7fLvvHn/DCkJXTEZoFCqo6ZW+e/cmqviMvouqF4dV5w="
            }
          },
          "93qI2zX64EJHBvbiRZLZJAor66Gw2OwOy3aIOLKDvCk=": {
            "valueMac": {
              "type": "Buffer",
              "data": "grN4VPVduJV9vrVV16CxIsPqzCWCiHdbC0FHqENWxB4="
            }
          },
          "6ZAFQfXtXGmdrTmB4PoGRcr52r0RpRJpTXnF01eFOMg=": {
            "valueMac": {
              "type": "Buffer",
              "data": "IXvqLyqjNezhCZjC/M8Ey5INLQrPKKgMfKOt4+/MCZo="
            }
          },
          "8umeKIpRncnEeKUnDTmukWeLKx4Q6swMb2x9Cn9zQyI=": {
            "valueMac": {
              "type": "Buffer",
              "data": "rdUDNMsZ0UZN9JBROKgJNO6SwNzoHCHsqR75DIIcHtM="
            }
          },
          "7KFKJr0uqJiWUQn3kOUgpF+bd8KHfpfmy9Jf717J/Tw=": {
            "valueMac": {
              "type": "Buffer",
              "data": "31EbbduonxHlc48FhZW7ugyDsKyqfsw2vZPJmKC57Vs="
            }
          },
          "4IsSfZz+W8nUWnXOeh4PS8HlUPuosTePPFbwwfWx9to=": {
            "valueMac": {
              "type": "Buffer",
              "data": "OFvaLrk4H/uZu2maHIXeLeW4a0c6oyRFRqNnrZ9cjuU="
            }
          },
          "Lar7/e6faMM3XzwdjF/iOUJ0M1O5Y1XgHaAEqC6CouI=": {
            "valueMac": {
              "type": "Buffer",
              "data": "vEdt4i6Dawv/z/piuZg15OV9wt1oM6kK0BZ2AoA5FDE="
            }
          },
          "/Xo/vf+ANloP4P9NSb3BjDSJc5W5gJBkQNLdkv+4Vl8=": {
            "valueMac": {
              "type": "Buffer",
              "data": "X6H/ev7G5JM5BqWFqxFYO0dCfwk2nyHkCk1wGAgtT4k="
            }
          },
          "yX53Zcp5ohoxOakQt1Ig+zVqnDzIr3hTB9mEpYIRAe8=": {
            "valueMac": {
              "type": "Buffer",
              "data": "tN+mCHLQDpEKayvLeU7rxgUb7hPpj963L9BqXPGH6q0="
            }
          },
          "quNsIJ7g0ecr0+S6vyYm9QmCtt00Sx7xEDehn7cAtek=": {
            "valueMac": {
              "type": "Buffer",
              "data": "/8i6CsfKlPiRRIlElGG0lMzk9xVU8BmTD0GG7GCQcWY="
            }
          },
          "iZSWcmrO3lHkcqwAxZ/teG9bXAiL3KlYHZ3hpGw0JDs=": {
            "valueMac": {
              "type": "Buffer",
              "data": "eMIwngbOQRqUwBl7dSdi6nrscR2K5RLglep/HEmVzwE="
            }
          },
          "i6m4XoJBnorOmnRvH7Gzh8GXR556ZMPiP7CARMHxnKU=": {
            "valueMac": {
              "type": "Buffer",
              "data": "VJdekOJ1w/fLZshQto8KBY+/cCvR0pzm1yzfw6inqe0="
            }
          },
          "u93C9NXCKLCTyUFkfVxLCvag+zABWAqpZZokU8UpdUQ=": {
            "valueMac": {
              "type": "Buffer",
              "data": "dmOvuz/RCooSOzjbnzkBAdY1CKMaUS+3yLnuXsnBr9U="
            }
          }
        }
      },
      "regular_low": {
        "version": 1,
        "hash": {
          "type": "Buffer",
          "data": "DdixiC3chM6VIV/G8+qSZQPFY7MCo8Xl7B5gFOHyOaYXltE5zYJ5o3YsnNRlIFDh7uuQdzkXGwThL7CaEdICIPgOHsa7RwOOWTyg2bx7L5rbuojzqTzUeIpKmOiZ8ShxbvRCQsyBlLtfDrDkptsCFPUe7id1HfhkDcdnpoiM7UE="
        },
        "indexValueMap": {
          "Qpt1Vk2aNdBqJL60SofgDF2kHLygXfQhspfNqgxYSVs=": {
            "valueMac": {
              "type": "Buffer",
              "data": "KAVmtCCGsHCeks+3jSkDDWpaM8WXeBYDaOgAwb4b1As="
            }
          }
        }
      }
    }
  }
}
